03/cpu/src/Def_BarrelShifter.v
// Constants used in the Barrel shifter

`define LogicalLeftShift     2'b00
`define LogicalRightShift    2'b01
`define ArithmeticRightShift 2'b10
`define RotateRightShift     2'b11

03/cpu/Def_StructureParameter.v
// Constants that define the architectural decisions and structure of
// instructions

`define WordWidth 32
`define ByteWidth 8
`define WordZero 32'h0000_0000

03/cpu/src/barrel_shifter.v
`include "Def_StructureParameter.v"
`include "Def_BarrelShifter.v"

// 32-bit barrel shifter used to shift and rotate n-bits within a single clock cycle.
// https://en.wikipedia.org/wiki/Barrel_shifter
//
// Eg of a pipelined shifter (6 clock cycles) just for reference:
// https://www.cs.uregina.ca/Links/class-info/301/guili/BarrelShPipeline.html
module barrel_shifter(in_Reg_val, in_Imm_val, in_Shift_val, in_Rotate, in_Shift_type, in_C_flag,
    out_Op2, out_Carry);
    // in_Shift_val: amount to be shifted by. if op2 is imm, amount = 4-bit rotate * 2, else it is
    //               5-bit shift amount
    // in_C_flag: C flag of CNZV (CPSR condition)
    // in_Reg_val: value to be shifted which comes from register
    // in_Imm_val: value to be shifted which comes from decoder 

    input  wire [`WordWidth-1:0] in_Reg_val; // register content
    input  wire [`WordWidth-1:0] in_Imm_val; // zero-padded imm8
    input  wire [1:0]            in_Shift_type;
    input  wire [4:0]            in_Shift_val;
    input  wire [3:0]            in_Rotate; // rotate to be applied to imm
    input  wire                  in_C_flag;
    output wire [`WordWidth-1:0] out_Op2;
    output wire                  out_Carry;

    reg [`WordWidth-1:0] r_Op2;
    reg                  r_Carry;

    assign out_Op2 = r_Op2;
    assign out_Carry = r_Carry;

    task exec_shift(input [`WordWidth-1:0] val, input [4:0] shift_val);
        begin
            if (shift_val == 0) begin
                case (in_Shift_type)
                    // LSL #0 is a special case, where the shifter carry out is the old value
                    // of the CPSR C flag. The contents of Rm are used directly as the second operand.
                    `LogicalLeftShift: begin
                        r_Carry = in_C_flag;
                        r_Op2 = val;
                    end

                    // LSR #0 is used to encode LSR #32. Logical shift right zero is redundant
                    // as it is the same as LSL #0, so the assembler will convert LSR #0
                    // (and ASR #0 and ROR #0) into LSL #0, and allow LSR #32 to be specified
                    `LogicalRightShift: begin
                        r_Carry = val[`WordWidth-1];
                        r_Op2 = `WordWidth'd0;
                    end

                    // Similar to LSR, except that the high bits are filled with bit 31 of Rm
                    // instead of zeros. This preserves the sign in 2’s complement notation
                    `ArithmeticRightShift: begin
                        // ASR #0 is used to encode ASR #32. Bit 31 of Rm is again used as the
                        // carry output, and each bit of operand 2 is also equal to bit 31 of Rm.
                        // The result is therefore all ones or all zeros, according to the value
                        // of bit 31 of Rm.
                        r_Carry = val[`WordWidth-1];
                        r_Op2 = {32{r_Carry}};
                    end

                    `RotateRightShift: begin
                        // The form of the shift field which might be expected to give ROR #0 is
                        // used to encode a special function of the barrel shifter, rotate right
                        // extended (RRX). This is a rotate right by one bit position of the 33 bit
                        // quantity formed by appending the CPSR C flag to the most significant
                        // end of the contents of Rm
                        r_Carry = val[0];
                        r_Op2 = {r_Carry, in_C_flag, val[`WordWidth-1:2]};
                    end
                endcase
            end
            else begin
                // Manually encode shift operations using concat of the input value instead of using shift
                // operators for efficiency I think. Using shift operations felt like cheating. It's
                // there in git history if you want to check it out.

                // $display("here %d %d", val, shift_val);
                r_Op2 = val;
                r_Carry = in_C_flag;

                // Shift 16 bits
                if (shift_val[4] == 1) begin
                    case (in_Shift_type)
                        `LogicalLeftShift: begin
                            r_Carry = r_Op2[`WordWidth-16];
                            r_Op2 = {r_Op2[`WordWidth-1-16:0], 16'h0000};
                        end

                        `LogicalRightShift: begin
                            r_Carry = r_Op2[15];
                            r_Op2 = {16'h0000, r_Op2[`WordWidth-1:16]};
                        end

                        `ArithmeticRightShift: begin
                            r_Carry = r_Op2[15];
                            r_Op2 = {{16{r_Op2[`WordWidth-1]}}, r_Op2[`WordWidth-1:16]};
                        end

                        `RotateRightShift: begin
                            r_Carry = r_Op2[15];
                            r_Op2 = {r_Op2[15:0], r_Op2[`WordWidth-1:16]};
                        end
                    endcase
                end

                // Shift 8 bits
                if (shift_val[3] == 1) begin
                    case (in_Shift_type)
                        `LogicalLeftShift: begin
                            r_Carry = r_Op2[`WordWidth-8];
                            r_Op2 = {r_Op2[`WordWidth-1-8:0], 8'h00};
                        end

                        `LogicalRightShift: begin
                            r_Carry = r_Op2[7];
                            r_Op2 = {8'h00, r_Op2[`WordWidth-1:8]};
                        end

                        `ArithmeticRightShift: begin
                            r_Carry = r_Op2[7];
                            r_Op2 = {{8{r_Op2[`WordWidth-1]}}, r_Op2[`WordWidth-1:8]};
                        end

                        `RotateRightShift: begin
                            r_Carry = r_Op2[7];
                            r_Op2 = {r_Op2[7:0], r_Op2[`WordWidth-1:8]};
                        end
                    endcase
                end

                // Shift 4 bits
                if (shift_val[2] == 1) begin
                    case (in_Shift_type)
                        `LogicalLeftShift: begin
                            r_Carry = r_Op2[`WordWidth-4];
                            r_Op2 = {r_Op2[`WordWidth-1-4:0], 4'h0};
                        end

                        `LogicalRightShift: begin
                            r_Carry = r_Op2[3];
                            r_Op2 = {4'h0, r_Op2[`WordWidth-1:4]};
                        end

                        `ArithmeticRightShift: begin
                            r_Carry = r_Op2[3];
                            r_Op2 = {{4{r_Op2[`WordWidth-1]}}, r_Op2[`WordWidth-1:4]};
                        end

                        `RotateRightShift: begin
                            r_Carry = r_Op2[3];
                            r_Op2 = {r_Op2[3:0], r_Op2[`WordWidth-1:4]};
                        end
                    endcase
                end

                // Shift 2 bits
                if (shift_val[1] == 1) begin
                    case (in_Shift_type)
                        `LogicalLeftShift: begin
                            r_Carry = r_Op2[`WordWidth-2];
                            r_Op2 = {r_Op2[`WordWidth-1-2:0], 2'b00};
                        end

                        `LogicalRightShift: begin
                            r_Carry = r_Op2[1];
                            r_Op2 = {2'b00, r_Op2[`WordWidth-1:2]};
                        end

                        `ArithmeticRightShift: begin
                            r_Carry = r_Op2[1];
                            r_Op2 = {{2{r_Op2[`WordWidth-1]}}, r_Op2[`WordWidth-1:2]};
                        end

                        `RotateRightShift: begin
                            r_Carry = r_Op2[1];
                            r_Op2 = {r_Op2[1:0], r_Op2[`WordWidth-1:2]};
                        end
                    endcase
                end

                // Shift 1 bit
                if (shift_val[0] == 1) begin
                    case (in_Shift_type)
                        `LogicalLeftShift: begin
                            r_Carry = r_Op2[`WordWidth-1];
                            r_Op2 = {r_Op2[`WordWidth-1-1:0], 1'b0};
                        end

                        `LogicalRightShift: begin
                            r_Carry = r_Op2[0];
                            r_Op2 = {1'b0, r_Op2[`WordWidth-1:1]};
                        end

                        `ArithmeticRightShift: begin
                            r_Carry = r_Op2[0];
                            r_Op2 = {r_Op2[`WordWidth-1], r_Op2[`WordWidth-1:1]};
                        end

                        `RotateRightShift: begin
                            r_Carry = r_Op2[0];
                            r_Op2 = {r_Op2[0], r_Op2[`WordWidth-1:1]};
                        end
                    endcase
                end
            end
        end
    endtask

    always @(in_Reg_val or in_Shift_val or in_Imm_val or in_Rotate or in_C_flag) begin
        if (in_Reg_val[0] !== 1'bX && in_Shift_val[0] !== 1'bX)
            exec_shift(in_Reg_val, in_Shift_val);
        else if (in_Imm_val[0] !== 1'bX && in_Rotate[0] !== 1'bX)
            exec_shift(in_Imm_val, in_Rotate);

    end
endmodule

03/cpu/testbench/shifter_tb.v
`include "src/Def_BarrelShifter.v"
`include "src/barrel_shifter.v"

module shifter_tb;
    reg  [`WordWidth-1:0] in_Reg_val;
    reg  [`WordWidth-1:0] in_Imm_val;
    reg  [4:0]            in_Shift_val;
    reg  [3:0]            in_Rotate;
    reg  [1:0]            in_Shift_type;
    reg                   in_C_flag;
    wire [`WordWidth-1:0] out_Op2;
    wire                  out_Carry;

    barrel_shifter shifter(in_Reg_val, in_Imm_val, in_Shift_val, in_Rotate, in_Shift_type, in_C_flag,
        out_Op2, out_Carry);

    initial begin
        $dumpfile("cpu.vcd");
        $dumpvars;
    end

    initial begin
        #100;
        $display("LSL 2, #1");
        in_Reg_val = 32'd2;
        in_Shift_type = `LogicalLeftShift;
        in_Shift_val = 1;
        in_C_flag = 0;
        #10;
        if (out_Op2 != 32'd4 || out_Carry != 1'b0)
            $display("---- Test failed, got %d", out_Op2);

        #100;
        $display("LSL 2, #0, (with carry 1)");
        in_Reg_val = 32'd2;
        in_Shift_type = `LogicalLeftShift;
        in_Shift_val = 0;
        in_C_flag = 1;
        #10;
        if (out_Op2 != 32'd2 || out_Carry != 1'b1)
            $display("---- Test failed, got %d and %b", out_Op2, out_Carry);

        #100;
        $display("LSR 2, #1");
        in_Reg_val = 32'd2;
        in_Shift_type = `LogicalRightShift;
        in_Shift_val = 1;
        in_C_flag = 0;
        #10;
        if (out_Op2 != 32'd1 || out_Carry != 1'b0)
            $display("---- Test failed, got %d", out_Op2);

        #100;
        $display("LSR 2, #0 (with carry 1)");
        in_Reg_val = 32'd2;
        in_Shift_type = `LogicalRightShift;
        in_Shift_val = 0;
        in_C_flag = 0;
        #10;
        if (out_Op2 != 32'd0 || out_Carry != in_Reg_val[31])
            $display("---- Test failed, got %d and %b", out_Op2, out_Carry);

        #100;
        $display("ASR 13244, #10 (with carry 1)");
        in_Reg_val = 32'd13244;
        in_Shift_type = `ArithmeticRightShift;
        in_Shift_val = 10;
        in_C_flag = 1;
        #10;
        if (out_Op2 != 32'd12 || out_Carry != 1'b1)
            $display("---- Test failed, got %b and %b", out_Op2, out_Carry);

        #100;
        $display("ASR 4290000000, #0");
        in_Reg_val = 32'd4290000000;
        in_Shift_type = `ArithmeticRightShift;
        in_Shift_val = 0;
        in_C_flag = 0;
        #10;
        if (out_Op2 != 32'b11111111111111111111111111111111 || out_Carry != 1'b1)
            $display("---- Test failed, got %b and %b", out_Op2, out_Carry);

        #100;
        $display("ROR 200, #4 (with carry 1)");
        in_Reg_val = 32'd200;
        in_Shift_type = `RotateRightShift;
        in_Shift_val = 4;
        in_C_flag = 1; // shouldn't matter
        #10;
        if (out_Op2 != 32'b10000000000000000000000000001100 || out_Carry != 1'b1)
            $display("---- Test failed, got %b and %b", out_Op2, out_Carry);

        #100;
        $display("ROR 200, #0 (with carry 0)");
        in_Reg_val = 32'd200;
        in_Shift_type = `RotateRightShift;
        in_Shift_val = 0;
        in_C_flag = 0;
        #10;
        if (out_Op2 != 32'd50 || out_Carry != 1'b0)
            $display("---- Test failed, got %d and %b", out_Op2, out_Carry);

        #100;
        $display("ROR 200, #0 (with carry 1)");
        in_Reg_val = 32'd200;
        in_C_flag = 1;
        in_Shift_type = `RotateRightShift;
        in_Shift_val = 0;
        #10;
        if (out_Op2 != 32'b01000000000000000000000000110010 || out_Carry != 1'b0)
            $display("---- Test failed, got %b and %b", out_Op2, out_Carry);

        #100;
        $finish;
    end
endmodule

03/cpu/cpu.vcd
$date
	Wed Jun 15 19:57:06 2022
$end
$version
	Icarus Verilog
$end
$timescale
	1s
$end
$scope module shifter_tb $end
$var wire 32 ! out_Op2 [31:0] $end
$var wire 1 " out_Carry $end
$var reg 1 # in_C_flag $end
$var reg 32 $ in_Imm_val [31:0] $end
$var reg 32 % in_Reg_val [31:0] $end
$var reg 4 & in_Rotate [3:0] $end
$var reg 2 ' in_Shift_type [1:0] $end
$var reg 5 ( in_Shift_val [4:0] $end
$scope module shifter $end
$var wire 1 # in_C_flag $end
$var wire 32 ) in_Imm_val [31:0] $end
$var wire 32 * in_Reg_val [31:0] $end
$var wire 4 + in_Rotate [3:0] $end
$var wire 2 , in_Shift_type [1:0] $end
$var wire 5 - in_Shift_val [4:0] $end
$var wire 1 " out_Carry $end
$var wire 32 . out_Op2 [31:0] $end
$var reg 1 / r_Carry $end
$var reg 32 0 r_Op2 [31:0] $end
$scope task exec_shift $end
$var reg 5 1 shift_val [4:0] $end
$var reg 32 2 val [31:0] $end
$upscope $end
$upscope $end
$upscope $end
$enddefinitions $end
#0
$dumpvars
bx 2
bx 1
bx 0
x/
bx .
bx -
bx ,
bx +
bx *
bx )
bx (
bx '
bx &
bx %
bx $
x#
x"
bx !
$end
#100
0"
0/
b100 !
b100 .
b100 0
b1 1
b10 2
0#
b1 (
b1 -
b0 '
b0 ,
b10 %
b10 *
#210
b10 !
b10 .
b10 0
1"
1/
b0 1
1#
b0 (
b0 -
#320
b1 !
b1 .
b1 0
0"
0/
b1 1
0#
b1 (
b1 -
b1 '
b1 ,
#430
b0 !
b0 .
b0 0
b0 1
b0 (
b0 -
#540
1"
1/
b1100 !
b1100 .
b1100 0
b1010 1
b11001110111100 2
1#
b1010 (
b1010 -
b10 '
b10 ,
b11001110111100 %
b11001110111100 *
#650
b11111111111111111111111111111111 !
b11111111111111111111111111111111 .
b11111111111111111111111111111111 0
b0 1
b11111111101101000011010010000000 2
0#
b0 (
b0 -
b11111111101101000011010010000000 %
b11111111101101000011010010000000 *
#760
b10000000000000000000000000001100 !
b10000000000000000000000000001100 .
b10000000000000000000000000001100 0
b100 1
b11001000 2
1#
b100 (
b100 -
b11 '
b11 ,
b11001000 %
b11001000 *
#870
b110010 !
b110010 .
b110010 0
0"
0/
b0 1
0#
b0 (
b0 -
#980
b1000000000000000000000000110010 !
b1000000000000000000000000110010 .
b1000000000000000000000000110010 0
1#
