03/cpu/Def_StructureParameter.v
// Constants that define the architectural decisions and structure of
// instructions

`define WordWidth 32
`define ByteWidth 8
`define WordZero 32'h0000_0000

03/cpu/src/Def_ALUType.v
// Constants that are using in the ALU

`define ALUType_And 4'b0000
`define ALUType_Eor 4'b0001
`define ALUType_Sub 4'b0010
`define ALUType_Rsb 4'b0011
`define ALUType_Add 4'b0100
`define ALUType_Adc 4'b0101
`define ALUType_Sbc 4'b0110
`define ALUType_Rsc 4'b0111
`define ALUType_Tst 4'b1000
`define ALUType_Teq 4'b1001
`define ALUType_Cmp 4'b1010
`define ALUType_Cmn 4'b1011
`define ALUType_Orr 4'b1100
`define ALUType_Mov 4'b1101
`define ALUType_Bic 4'b1110
`define ALUType_Mvn 4'b1111

03/cpu/adder.v
`include "Def_StructureParameter.v"

module adder(in_Rn, in_Op2, in_Carry, out_Y, out_CNZV);
    input   wire [`WordWidth-1:0] in_Rn;
    input   wire [`WordWidth-1:0] in_Op2;
    input   wire                  in_Carry;
    output  wire [`WordWidth-1:0] out_Y;
    output  wire [3:0]            out_CNZV;

    reg [`WordWidth-1:0] r_Y;
    reg [3:0]            r_CNZV;

    function [1:0] one_bit_add (input a, b, carry);
        begin
            case ({a, b, carry})
                3'b000:
                    one_bit_add = 2'b00;
                3'b001:
                    one_bit_add = 2'b01;
                3'b010:
                    one_bit_add = 2'b01;
                3'b011:
                    one_bit_add = 2'b10;
                3'b100:
                    one_bit_add = 2'b01;
                3'b101:
                    one_bit_add = 2'b10;
                3'b110:
                    one_bit_add = 2'b10;
                3'b111:
                    one_bit_add = 2'b11;
            endcase
        end
    endfunction // one_bit_adder

    integer idx;

    always @(in_Rn or in_Op2 or in_Carry)
    begin
        // Add operands bit by bit taking care of carry
        for (idx = 0; idx < `WordWidth; idx = idx + 1)
        begin
            if (idx == 0)
                r_CNZV[3] = in_Carry;

            {r_CNZV[3], r_Y[idx]} = one_bit_add(in_Rn[idx], in_Op2[idx], r_CNZV[3]);
        end // for loop

        r_CNZV[2] = r_Y[`WordWidth-1];

        if (r_Y == `WordZero)
            r_CNZV[1] = 1'b1;
        else
            r_CNZV[1] = 1'b0;

        if (in_Rn[`WordWidth-1] == in_Op2[`WordWidth-1] && r_Y[`WordWidth-1] != in_Rn[`WordWidth-1])
            r_CNZV[0] = 1'b1;
        else
            r_CNZV[0] = 1'b0;
    end // always

    assign out_Y = r_Y;
    assign out_CNZV = r_CNZV;
endmodule //adder

03/cpu/src/alu.v
`include "Def_ALUType.v"
`include "Def_StructureParameter.v"
`include "adder.v"

module alu(in_Rn, in_Op2, in_Carry, in_Opcode, out_Y, out_CNZV);
    input   wire  [`WordWidth-1:0]  in_Rn;      // (operand 1) register
    input   wire  [`WordWidth-1:0]  in_Op2;     // (operand 2) shifted register or imm
    input   wire                    in_Carry;   // carry from barrel shifter (status)
    input   wire  [3:0]             in_Opcode;  // opcode
    output  wire  [`WordWidth-1:0]  out_Y;      // result
    output  wire  [3:0]             out_CNZV;   // condition status register. eg out_CNZV[3] = c, out_CNZV[2] = n...

    reg [`WordWidth-1:0] r_Y;
    reg [3:0]            r_CNZV;
    // Adder registers
    reg [`WordWidth-1:0]  ad_Rn;
    reg [`WordWidth-1:0]  ad_Op2;
    reg                   ad_Carry;
    wire [`WordWidth-1:0] ad_Y;
    wire [3:0]            ad_CNZV;

    adder adder(ad_Rn, ad_Op2, ad_Carry, ad_Y, ad_CNZV);

    always @(*)
    begin
        ad_Rn = `WordZero;
        ad_Op2 = `WordZero;
        ad_Carry = 1'b0;
        r_Y = `WordZero;
        r_CNZV = 4'b0000;

        case (in_Opcode)
            // AND: operand1 AND operand2
            // TST: as AND, but result is not written
            `ALUType_And, `ALUType_Tst: begin
                r_Y = in_Rn & in_Op2;
                r_CNZV[3] = in_Carry;
                r_CNZV[2] = r_Y[`WordWidth-1];
                r_CNZV[1] = (r_Y == 0);
            end

            // EOR: operand1 EOR operand2
            // TEQ: as EOR, but result is not written
            `ALUType_Eor, `ALUType_Teq: begin
                r_Y = in_Rn ^ in_Op2;
                r_CNZV[3] = in_Carry;
                r_CNZV[2] = r_Y[`WordWidth-1];
                r_CNZV[1] = (r_Y == 0);
            end

            // SUB: operand1 - operand2
            // CMP: as SUB, but result is not written
            `ALUType_Sub, `ALUType_Cmp: begin
                ad_Op2 = -in_Op2;
                r_Y = ad_Y;
                r_CNZV = ad_CNZV;
            end

            // operand2 - operand1
            `ALUType_Rsb: begin
                ad_Rn = -in_Rn;
                ad_Op2 = in_Op2;
                r_Y = ad_Y;
                r_CNZV = ad_CNZV;
            end

            // ADD: operand1 + operand2
            // CMD: as ADD, but result is not written
            `ALUType_Add, `ALUType_Cmn: begin
                ad_Rn = in_Rn;
                ad_Op2 = in_Op2;
                r_Y = ad_Y;
                r_CNZV = ad_CNZV;
            end

            // operand1 + operand2 + carry
            `ALUType_Adc: begin
                ad_Rn = in_Rn;
                ad_Op2 = in_Op2;
                ad_Carry = in_Carry;
                r_Y = ad_Y;
                r_CNZV = ad_CNZV;
            end

            // operand1 - operand2 + carry - 1
            `ALUType_Sbc: begin
                ad_Rn = in_Rn;
                ad_Op2 = -in_Op2;
                ad_Carry = in_Carry;
                r_Y = ad_Y - 1;
                r_CNZV = ad_CNZV;
            end

            // operand2 - operand1 + carry - 1
            `ALUType_Rsc: begin
                ad_Rn = -in_Rn;
                ad_Op2 = in_Op2;
                ad_Carry = in_Carry;
                r_Y = ad_Y - 1;
                r_CNZV = ad_CNZV;
            end

            // operand1 OR operand2
            `ALUType_Orr: begin
                r_Y = in_Rn | in_Op2;
                r_CNZV[3] = in_Carry;
                r_CNZV[2] = r_Y[`WordWidth-1];
                r_CNZV[1] = (r_Y == 0);
            end

            // operand2 (operand1 is ignored)
            `ALUType_Mov: begin
                r_Y = in_Op2;
                r_CNZV[3] = in_Carry;
                r_CNZV[2] = r_Y[`WordWidth-1];
                r_CNZV[1] = (r_Y == 0);
            end

            // operand1 AND NOT operand2 (Bit clear)
            `ALUType_Bic: begin
                r_Y <= in_Rn & ~in_Op2;
                r_CNZV[3] <= in_Carry;
                r_CNZV[2] <= r_Y[`WordWidth-1];
                r_CNZV[1] <= (r_Y == 0);
            end

            // NOT operand2 (operand1 is ignored)
            `ALUType_Mvn: begin
                r_Y = ~in_Op2;
                r_CNZV[3] = in_Carry;
                r_CNZV[2] = r_Y[`WordWidth-1];
                r_CNZV[1] = (r_Y == 0);
            end
        endcase
    end // always

    assign out_Y = r_Y;
    assign out_CNZV = r_CNZV;
endmodule // alu

03/cpu/testbench/alu_tb.v
`include "src/Def_StructureParameter.v"
`include "src/alu.v"

module alu_tb;

    reg  [`WordWidth-1:0]  in_Rn;
    reg  [`WordWidth-1:0]  in_Op2;
    reg                    in_Carry;
    reg  [3:0]             in_Opcode;
    wire [`WordWidth-1:0]  out_Y;
    wire [3:0]             out_CNZV;

    alu a(in_Rn, in_Op2, in_Carry, in_Opcode, out_Y, out_CNZV);

    initial
    begin
        $dumpfile("cpu.vcd");
        $dumpvars;
    end

    initial
    begin
        #100;
        $display("ADD 1, 1");
        in_Rn = `WordWidth'd1;
        in_Op2 = `WordWidth'd1;
        in_Carry = 1'b0;
        in_Opcode = 4'b0100;

        #100;
        $display("ADD 2, 3");
        in_Rn = `WordWidth'd2;
        in_Op2 = `WordWidth'd3;
        in_Carry = 1'b0;

        #100;
        if (out_Y == `WordWidth'd5)
            $display("Test passed! Sum is %d", out_Y);
        else
            $display("Test failed! %d", out_Y);

        $finish;
    end
endmodule

03/cpu/cpu.vcd
$date
	Sat Jun 11 22:27:06 2022
$end
$version
	Icarus Verilog
$end
$timescale
	1s
$end
$scope module alu_tb $end
$var wire 32 ! out_Y [31:0] $end
$var wire 4 " out_CNZV [3:0] $end
$var reg 1 # in_Carry $end
$var reg 32 $ in_Op2 [31:0] $end
$var reg 4 % in_Opcode [3:0] $end
$var reg 32 & in_Rn [31:0] $end
$scope module a $end
$var wire 1 # in_Carry $end
$var wire 32 ' in_Op2 [31:0] $end
$var wire 4 ( in_Opcode [3:0] $end
$var wire 32 ) in_Rn [31:0] $end
$var wire 4 * out_CNZV [3:0] $end
$var wire 32 + out_Y [31:0] $end
$var wire 32 , ad_Y [31:0] $end
$var wire 4 - ad_CNZV [3:0] $end
$var reg 1 . ad_Carry $end
$var reg 32 / ad_Op2 [31:0] $end
$var reg 32 0 ad_Rn [31:0] $end
$var reg 4 1 r_CNZV [3:0] $end
$var reg 32 2 r_Y [31:0] $end
$scope module adder $end
$var wire 1 . in_Carry $end
$var wire 32 3 in_Op2 [31:0] $end
$var wire 32 4 in_Rn [31:0] $end
$var wire 4 5 out_CNZV [3:0] $end
$var wire 32 6 out_Y [31:0] $end
$var reg 4 7 r_CNZV [3:0] $end
$var reg 32 8 r_Y [31:0] $end
$var integer 32 9 idx [31:0] $end
$scope function one_bit_add $end
$var reg 1 : a $end
$var reg 1 ; b $end
$var reg 1 < carry $end
$upscope $end
$upscope $end
$upscope $end
$upscope $end
$enddefinitions $end
#0
$dumpvars
x<
x;
x:
b0 9
b0 8
b0 7
b0 6
b0 5
b0 4
b0 3
b0 2
b0 1
b0 0
b0 /
0.
b0 -
b0 ,
b0 +
b0 *
bx )
bx (
bx '
bx &
bx %
bx $
x#
b0 "
b0 !
$end
#1
b1 9
0:
0;
0<
#2
b10 9
#3
b11 9
#4
b100 9
#5
b101 9
#6
b110 9
#7
b111 9
#8
b1000 9
#9
b1001 9
#10
b1010 9
#11
b1011 9
#12
b1100 9
#13
b1101 9
#14
b1110 9
#15
b1111 9
#16
b10000 9
#17
b10001 9
#18
b10010 9
#19
b10011 9
#20
b10100 9
#21
b10101 9
#22
b10110 9
#23
b10111 9
#24
b11000 9
#25
b11001 9
#26
b11010 9
#27
b11011 9
#28
b11100 9
#29
b11101 9
#30
b11110 9
#31
b11111 9
#32
b10 -
b10 5
b10 7
b100000 9
#100
b0 9
b10 "
b10 *
b10 1
b1 /
b1 3
b1 0
b1 4
b100 %
b100 (
0#
b1 $
b1 '
b1 &
b1 )
#101
b1010 "
b1010 *
b1010 1
b1 /
b1 3
b1 0
b1 4
b1 9
b1010 -
b1010 5
b1010 7
1:
1;
#102
b10 !
b10 +
b10 2
b10 "
b10 *
b10 1
b1 /
b1 3
b1 0
b1 4
b10 9
b10 -
b10 5
b10 7
b10 ,
b10 6
b10 8
0:
0;
1<
#103
b11 9
0<
#104
b100 9
#105
b101 9
#106
b110 9
#107
b111 9
#108
b1000 9
#109
b1001 9
#110
b1010 9
#111
b1011 9
#112
b1100 9
#113
b1101 9
#114
b1110 9
#115
b1111 9
#116
b10000 9
#117
b10001 9
#118
b10010 9
#119
b10011 9
#120
b10100 9
#121
b10101 9
#122
b10110 9
#123
b10111 9
#124
b11000 9
#125
b11001 9
#126
b11010 9
#127
b11011 9
#128
b11100 9
#129
b11101 9
#130
b11110 9
#131
b11111 9
#132
b0 "
b0 *
b0 1
b10 !
b10 +
b10 2
b1 /
b1 3
b1 0
b1 4
b0 -
b0 5
b0 7
b0 9
#133
b1000 "
b1000 *
b1000 1
b10 !
b10 +
b10 2
b1 /
b1 3
b1 0
b1 4
b1 9
b1000 -
b1000 5
b1000 7
1:
1;
#134
b0 "
b0 *
b0 1
b10 !
b10 +
b10 2
b1 /
b1 3
b1 0
b1 4
b10 9
b0 -
b0 5
b0 7
0:
0;
1<
#135
b11 9
0<
#136
b100 9
#137
b101 9
#138
b110 9
#139
b111 9
#140
b1000 9
#141
b1001 9
#142
b1010 9
#143
b1011 9
#144
b1100 9
#145
b1101 9
#146
b1110 9
#147
b1111 9
#148
b10000 9
#149
b10001 9
#150
b10010 9
#151
b10011 9
#152
b10100 9
#153
b10101 9
#154
b10110 9
#155
b10111 9
#156
b11000 9
#157
b11001 9
#158
b11010 9
#159
b11011 9
#160
b11100 9
#161
b11101 9
#162
b11110 9
#163
b11111 9
#164
b100000 9
#200
b0 9
b10 !
b10 +
b10 2
b11 /
b11 3
b10 0
b10 4
b11 $
b11 '
b10 &
b10 )
#201
b11 !
b11 +
b11 2
b11 /
b11 3
b10 0
b10 4
b1 9
b11 ,
b11 6
b11 8
1;
#202
b1000 "
b1000 *
b1000 1
b1 !
b1 +
b1 2
b11 /
b11 3
b10 0
b10 4
b10 9
b1000 -
b1000 5
b1000 7
b1 ,
b1 6
b1 8
1:
#203
b0 "
b0 *
b0 1
b101 !
b101 +
b101 2
b11 /
b11 3
b10 0
b10 4
b11 9
b0 -
b0 5
b0 7
b101 ,
b101 6
b101 8
0:
0;
1<
#204
b100 9
0<
#205
b101 9
#206
b110 9
#207
b111 9
#208
b1000 9
#209
b1001 9
#210
b1010 9
#211
b1011 9
#212
b1100 9
#213
b1101 9
#214
b1110 9
#215
b1111 9
#216
b10000 9
#217
b10001 9
#218
b10010 9
#219
b10011 9
#220
b10100 9
#221
b10101 9
#222
b10110 9
#223
b10111 9
#224
b11000 9
#225
b11001 9
#226
b11010 9
#227
b11011 9
#228
b11100 9
#229
b11101 9
#230
b11110 9
#231
b11111 9
#232
b100000 9
