02/led/led.v
module blinking(clock, led);
    input clock;
    output reg led;

    reg [31:0] counter;

    initial
    begin
        led = 1'b0;
        counter <= 32'b0;
    end

    always @(posedge clock)
    begin
        counter <= counter + 1'b1;
        // if (counter > 50000000) // 50Mhz clock
        if (counter > 10) // for testbench
        begin
            led <= ~led;
            counter <= 32'b0;
        end
    end
endmodule

02/led/test_bench.v
`timescale 10ms/1ms
module blinking_led;
    input wire led;
    output reg clock;

    blinking bl(clock, led);

    initial
        clock = 1'b0;

    always
        #10 clock <= ~clock;

    initial
    begin
        $monitor($time, " clock = %b, led = %b", clock, led);
        #1000 $finish;
    end

    initial
    begin
        $dumpfile("blinking.vcd");
        $dumpvars;
    end
endmodule

02/led/blinking.vcd
$date
	Thu Jun  9 16:26:06 2022
$end
$version
	Icarus Verilog
$end
$timescale
	1ms
$end
$scope module blinking_led $end
$var wire 1 ! led $end
$var reg 1 " clock $end
$scope module bl $end
$var wire 1 " clock $end
$var reg 32 # counter [31:0] $end
$var reg 1 ! led $end
$upscope $end
$upscope $end
$enddefinitions $end
#0
$dumpvars
b0 #
0"
0!
$end
#100
b1 #
1"
#200
0"
#300
b10 #
1"
#400
0"
#500
b11 #
1"
#600
0"
#700
b100 #
1"
#800
0"
#900
b101 #
1"
#1000
0"
#1100
b110 #
1"
#1200
0"
#1300
b111 #
1"
#1400
0"
#1500
b1000 #
1"
#1600
0"
#1700
b1001 #
1"
#1800
0"
#1900
b1010 #
1"
#2000
0"
#2100
b1011 #
1"
#2200
0"
#2300
1!
b0 #
1"
#2400
0"
#2500
b1 #
1"
#2600
0"
#2700
b10 #
1"
#2800
0"
#2900
b11 #
1"
#3000
0"
#3100
b100 #
1"
#3200
0"
#3300
b101 #
1"
#3400
0"
#3500
b110 #
1"
#3600
0"
#3700
b111 #
1"
#3800
0"
#3900
b1000 #
1"
#4000
0"
#4100
b1001 #
1"
#4200
0"
#4300
b1010 #
1"
#4400
0"
#4500
b1011 #
1"
#4600
0"
#4700
0!
b0 #
1"
#4800
0"
#4900
b1 #
1"
#5000
0"
#5100
b10 #
1"
#5200
0"
#5300
b11 #
1"
#5400
0"
#5500
b100 #
1"
#5600
0"
#5700
b101 #
1"
#5800
0"
#5900
b110 #
1"
#6000
0"
#6100
b111 #
1"
#6200
0"
#6300
b1000 #
1"
#6400
0"
#6500
b1001 #
1"
#6600
0"
#6700
b1010 #
1"
#6800
0"
#6900
b1011 #
1"
#7000
0"
#7100
1!
b0 #
1"
#7200
0"
#7300
b1 #
1"
#7400
0"
#7500
b10 #
1"
#7600
0"
#7700
b11 #
1"
#7800
0"
#7900
b100 #
1"
#8000
0"
#8100
b101 #
1"
#8200
0"
#8300
b110 #
1"
#8400
0"
#8500
b111 #
1"
#8600
0"
#8700
b1000 #
1"
#8800
0"
#8900
b1001 #
1"
#9000
0"
#9100
b1010 #
1"
#9200
0"
#9300
b1011 #
1"
#9400
0"
#9500
0!
b0 #
1"
#9600
0"
#9700
b1 #
1"
#9800
0"
#9900
b10 #
1"
