02/uart/receiver.v
module receiver
    #(parameter CLOCKS_PER_BIT = 0)
    (
        input wire clock,
        input wire serial,
        output [7:0] w_rx_byte
    );

    parameter IDLE_STATE = 3'b000;
    parameter START_STATE = 3'b001;
    parameter DATA_STATE = 3'b010;
    parameter STOP_STATE = 3'b100;
    parameter CLEANUP_STATE = 3'b101;

    reg [8:0] r_clock_count;
    reg [2:0] r_rx_state;
    reg [2:0] r_bit_index;
    reg [7:0] r_rx_byte;

    initial
    begin
        r_rx_state <= IDLE_STATE;
    end

    always @(posedge clock)
    begin
        case (r_rx_state)
            IDLE_STATE:
            begin
                r_clock_count <= 0;
                r_bit_index <= 0;

                if (serial == 1'b0)
                    r_rx_state <= START_STATE;
            end // IDLE_STATE

            START_STATE:
            begin
                // If the apparent start bit lasts at least one-half of the bit time, it is valid
                // and signals the start of a new character. If not, it is considered a spurious
                // pulse and is ignored.
                if (r_clock_count == CLOCKS_PER_BIT/2)
                begin
                    if (serial == 0)
                    begin
                        r_clock_count <= 0;
                        r_rx_state = DATA_STATE;
                    end
                    else
                        r_rx_state = IDLE_STATE;
                end
                else
                    r_clock_count <= r_clock_count + 1;
            end // START_STATE

            DATA_STATE:
            begin
                if (r_clock_count < CLOCKS_PER_BIT)
                    r_clock_count <= r_clock_count + 1;
                else
                begin
                    r_rx_byte[r_bit_index] = serial;
                    r_clock_count <= 0;

                    if (r_bit_index == 7)
                    begin
                        r_rx_state <= STOP_STATE;
                        r_bit_index <= 0;
                    end
                    else
                        r_bit_index <= r_bit_index + 1;
                end
            end // DATA_STATE

            STOP_STATE:
            begin
                if (r_clock_count < CLOCKS_PER_BIT)
                    r_clock_count <= r_clock_count + 1;
                else
                begin
                    if (serial == 1'b1)
                    begin
                        r_rx_state <= CLEANUP_STATE;
                        r_clock_count <= 0;
                    end
                end
            end // STOP_STATE

            CLEANUP_STATE:
            begin
                r_rx_state <= IDLE_STATE;
            end // CLEANUP_STATE

            default:
                r_rx_state <= IDLE_STATE;
        endcase
    end

    assign w_rx_byte = r_rx_byte;
endmodule

02/uart/transmitter.v
module transmitter
    #(parameter CLOCKS_PER_BIT = 0)
    (
        input wire clock,
        input wire tx_bit,
        input [7:0] tx_data_byte,
        output reg serial,
        output wire tx_done
    );

    parameter IDLE_STATE = 3'b000;
    parameter START_STATE = 3'b001;
    parameter DATA_STATE = 3'b010;
    parameter STOP_STATE = 3'b100;
    parameter CLEANUP_STATE = 3'b101;

    reg [8:0] r_clock_count;
    reg [2:0] r_tx_state;
    reg [2:0] r_bit_index;
    reg [7:0] r_tx_byte;
    reg r_tx_done;

    initial
    begin
        r_clock_count = 0;
        r_tx_state = 3'b0;
        r_bit_index = 0;
        r_tx_done = 0;
    end

    always @(posedge clock)
    begin
        case (r_tx_state)
            IDLE_STATE:
            begin
                serial = 1'b1; // Drive line HIGH
                r_tx_done = 1'b0;
                r_bit_index = 0;

                if (tx_bit == 1'b1) // idle active bit
                begin
                    r_tx_byte <= tx_data_byte;
                    r_tx_state <= START_STATE;
                end
                else
                    r_tx_state <= IDLE_STATE;
            end // IDLE_STATE

            START_STATE:
            begin
                serial = 1'b0; // start bit = 0

                if (r_clock_count < CLOCKS_PER_BIT)
                    r_clock_count <= r_clock_count + 1;
                else
                begin
                    r_clock_count <= 0;
                    r_tx_state <= DATA_STATE;
                end
            end // START_STATE

            DATA_STATE:
            begin
                serial <= r_tx_byte[r_bit_index];

                if (r_clock_count < CLOCKS_PER_BIT)
                    r_clock_count <= r_clock_count + 1;
                else
                begin
                    r_clock_count <= 0;
                    if (r_bit_index == 7)
                    begin
                        r_bit_index <= 0;
                        r_tx_state <= STOP_STATE;
                    end
                    else
                        r_bit_index <= r_bit_index + 1;
                end
            end // DATA_STATE

            STOP_STATE:
            begin
                serial <= 1'b1;

                if (r_clock_count < CLOCKS_PER_BIT)
                    r_clock_count <= r_clock_count + 1;
                else
                begin
                    r_clock_count <= 0;
                    r_tx_state <= CLEANUP_STATE;
                end
            end // STOP_STATE

            CLEANUP_STATE:
            begin
                r_tx_done <= 1'b1;
                r_tx_state <= IDLE_STATE;
            end // CLEANUP_STATE

            default:
                r_tx_state <= IDLE_STATE;
        endcase
    end

    assign tx_done = r_tx_done;
endmodule

02/uart/testbench.v
// A UART transmitter and receiver built with a 50MHz clock which sends a byte
// of data asynchronously.
// https://en.wikipedia.org/wiki/Universal_asynchronous_receiver-transmitter

`timescale 1ns/1ps
module uart_test_bench;

    // 50Mhz clock
    parameter CLOCK_FREQ = 50000000;
    parameter BAUD = 9600; // bits per second
    // CLOCKS_PER_BIT = CLOCK_FREQ / UART Freq
    parameter CLOCKS_PER_BIT = CLOCK_FREQ / (16 * BAUD); 

    reg r_clock;
    reg r_tx_bit;
    reg [7:0] r_tx_byte;
    wire serial;
    wire r_tx_done;
    wire [7:0] w_rx_byte;

    transmitter #(.CLOCKS_PER_BIT(CLOCKS_PER_BIT)) tx (
        .clock(r_clock),
        .tx_bit(r_tx_bit),
        .tx_data_byte(r_tx_byte),
        .serial(serial),
        .tx_done(r_tx_done)
    );
    receiver #(.CLOCKS_PER_BIT(CLOCKS_PER_BIT)) rx (
        .clock(r_clock),
        .serial(serial),
        .w_rx_byte(w_rx_byte)
    );

    initial
    begin
        r_clock = 0;
    end

    always
        #(CLOCK_FREQ/2) r_clock = ~r_clock;

    initial
    begin
        $dumpfile("uart.vcd");
        $dumpvars;
    end

    initial
    begin
        #1;
        // Test transmitter
        @(posedge r_clock);
        @(posedge r_clock);
        r_tx_bit <= 1'b1; // idle active bit
        r_tx_byte <= 8'hAB; // data
        @(posedge r_clock);
        r_tx_bit <= 1'b0; // stop bit
        @(posedge r_tx_done);
        $display("Transmitter sent \"%h\".", 8'hAB);

        // Test receiver
        if (w_rx_byte == 8'hAB)
            $display("Test passed! Received \"%h\"", w_rx_byte);
        else
            $display("Test failed! Received \"%h\"", w_rx_byte);

        $finish;
    end
endmodule

02/uart/uart.vcd
$date
	Thu Jun  9 21:12:08 2022
$end
$version
	Icarus Verilog
$end
$timescale
	1ps
$end
$scope module uart_test_bench $end
$var wire 8 ! w_rx_byte [7:0] $end
$var wire 1 " serial $end
$var wire 1 # r_tx_done $end
$var reg 1 $ r_clock $end
$var reg 1 % r_tx_bit $end
$var reg 8 & r_tx_byte [7:0] $end
$scope module rx $end
$var wire 1 $ clock $end
$var wire 8 ' w_rx_byte [7:0] $end
$var wire 1 " serial $end
$var reg 3 ( r_bit_index [2:0] $end
$var reg 9 ) r_clock_count [8:0] $end
$var reg 8 * r_rx_byte [7:0] $end
$var reg 3 + r_rx_state [2:0] $end
$upscope $end
$scope module tx $end
$var wire 1 $ clock $end
$var wire 1 % tx_bit $end
$var wire 8 , tx_data_byte [7:0] $end
$var wire 1 # tx_done $end
$var reg 3 - r_bit_index [2:0] $end
$var reg 9 . r_clock_count [8:0] $end
$var reg 8 / r_tx_byte [7:0] $end
$var reg 1 0 r_tx_done $end
$var reg 3 1 r_tx_state [2:0] $end
$var reg 1 " serial $end
$upscope $end
$upscope $end
$enddefinitions $end
#0
$dumpvars
b0 1
00
bx /
b0 .
b0 -
bx ,
b0 +
bx *
bx )
bx (
bx '
bx &
x%
0$
0#
x"
bx !
$end
#25000000000
b0 (
b0 )
1"
1$
#50000000000
0$
#75000000000
b10101011 &
b10101011 ,
1%
1$
#100000000000
0$
#125000000000
b1 1
b10101011 /
0%
1$
#150000000000
0$
#175000000000
b1 +
b1 .
0"
1$
#200000000000
0$
#225000000000
b10 .
b1 )
1$
#250000000000
0$
#275000000000
b10 )
b11 .
1$
#300000000000
0$
#325000000000
b100 .
b11 )
1$
#350000000000
0$
#375000000000
b100 )
b101 .
1$
#400000000000
0$
#425000000000
b110 .
b101 )
1$
#450000000000
0$
#475000000000
b110 )
b111 .
1$
#500000000000
0$
#525000000000
b1000 .
b111 )
1$
#550000000000
0$
#575000000000
b1000 )
b1001 .
1$
#600000000000
0$
#625000000000
b1010 .
b1001 )
1$
#650000000000
0$
#675000000000
b1010 )
b1011 .
1$
#700000000000
0$
#725000000000
b1100 .
b1011 )
1$
#750000000000
0$
#775000000000
b1100 )
b1101 .
1$
#800000000000
0$
#825000000000
b1110 .
b1101 )
1$
#850000000000
0$
#875000000000
b1110 )
b1111 .
1$
#900000000000
0$
#925000000000
b10000 .
b1111 )
1$
#950000000000
0$
#975000000000
b10000 )
b10001 .
1$
#1000000000000
0$
#1025000000000
b10010 .
b10001 )
1$
#1050000000000
0$
#1075000000000
b10010 )
b10011 .
1$
#1100000000000
0$
#1125000000000
b10100 .
b10011 )
1$
#1150000000000
0$
#1175000000000
b10100 )
b10101 .
1$
#1200000000000
0$
#1225000000000
b10110 .
b10101 )
1$
#1250000000000
0$
#1275000000000
b10110 )
b10111 .
1$
#1300000000000
0$
#1325000000000
b11000 .
b10111 )
1$
#1350000000000
0$
#1375000000000
b11000 )
b11001 .
1$
#1400000000000
0$
#1425000000000
b11010 .
b11001 )
1$
#1450000000000
0$
#1475000000000
b11010 )
b11011 .
1$
#1500000000000
0$
#1525000000000
b11100 .
b11011 )
1$
#1550000000000
0$
#1575000000000
b11100 )
b11101 .
1$
#1600000000000
0$
#1625000000000
b11110 .
b11101 )
1$
#1650000000000
0$
#1675000000000
b11110 )
b11111 .
1$
#1700000000000
0$
#1725000000000
b100000 .
b11111 )
1$
#1750000000000
0$
#1775000000000
b100000 )
b100001 .
1$
#1800000000000
0$
#1825000000000
b100010 .
b100001 )
1$
#1850000000000
0$
#1875000000000
b100010 )
b100011 .
1$
#1900000000000
0$
#1925000000000
b100100 .
b100011 )
1$
#1950000000000
0$
#1975000000000
b100100 )
b100101 .
1$
#2000000000000
0$
#2025000000000
b100110 .
b100101 )
1$
#2050000000000
0$
#2075000000000
b100110 )
b100111 .
1$
#2100000000000
0$
#2125000000000
b101000 .
b100111 )
1$
#2150000000000
0$
#2175000000000
b101000 )
b101001 .
1$
#2200000000000
0$
#2225000000000
b101010 .
b101001 )
1$
#2250000000000
0$
#2275000000000
b101010 )
b101011 .
1$
#2300000000000
0$
#2325000000000
b101100 .
b101011 )
1$
#2350000000000
0$
#2375000000000
b101100 )
b101101 .
1$
#2400000000000
0$
#2425000000000
b101110 .
b101101 )
1$
#2450000000000
0$
#2475000000000
b101110 )
b101111 .
1$
#2500000000000
0$
#2525000000000
b110000 .
b101111 )
1$
#2550000000000
0$
#2575000000000
b110000 )
b110001 .
1$
#2600000000000
0$
#2625000000000
b110010 .
b110001 )
1$
#2650000000000
0$
#2675000000000
b110010 )
b110011 .
1$
#2700000000000
0$
#2725000000000
b110100 .
b110011 )
1$
#2750000000000
0$
#2775000000000
b110100 )
b110101 .
1$
#2800000000000
0$
#2825000000000
b110110 .
b110101 )
1$
#2850000000000
0$
#2875000000000
b110110 )
b110111 .
1$
#2900000000000
0$
#2925000000000
b111000 .
b110111 )
1$
#2950000000000
0$
#2975000000000
b111000 )
b111001 .
1$
#3000000000000
0$
#3025000000000
b111010 .
b111001 )
1$
#3050000000000
0$
#3075000000000
b111010 )
b111011 .
1$
#3100000000000
0$
#3125000000000
b111100 .
b111011 )
1$
#3150000000000
0$
#3175000000000
b111100 )
b111101 .
1$
#3200000000000
0$
#3225000000000
b111110 .
b111101 )
1$
#3250000000000
0$
#3275000000000
b111110 )
b111111 .
1$
#3300000000000
0$
#3325000000000
b1000000 .
b111111 )
1$
#3350000000000
0$
#3375000000000
b1000000 )
b1000001 .
1$
#3400000000000
0$
#3425000000000
b1000010 .
b1000001 )
1$
#3450000000000
0$
#3475000000000
b1000010 )
b1000011 .
1$
#3500000000000
0$
#3525000000000
b1000100 .
b1000011 )
1$
#3550000000000
0$
#3575000000000
b1000100 )
b1000101 .
1$
#3600000000000
0$
#3625000000000
b1000110 .
b1000101 )
1$
#3650000000000
0$
#3675000000000
b1000110 )
b1000111 .
1$
#3700000000000
0$
#3725000000000
b1001000 .
b1000111 )
1$
#3750000000000
0$
#3775000000000
b1001000 )
b1001001 .
1$
#3800000000000
0$
#3825000000000
b1001010 .
b1001001 )
1$
#3850000000000
0$
#3875000000000
b1001010 )
b1001011 .
1$
#3900000000000
0$
#3925000000000
b1001100 .
b1001011 )
1$
#3950000000000
0$
#3975000000000
b1001100 )
b1001101 .
1$
#4000000000000
0$
#4025000000000
b1001110 .
b1001101 )
1$
#4050000000000
0$
#4075000000000
b1001110 )
b1001111 .
1$
#4100000000000
0$
#4125000000000
b1010000 .
b1001111 )
1$
#4150000000000
0$
#4175000000000
b1010000 )
b1010001 .
1$
#4200000000000
0$
#4225000000000
b1010010 .
b1010001 )
1$
#4250000000000
0$
#4275000000000
b1010010 )
b1010011 .
1$
#4300000000000
0$
#4325000000000
b1010100 .
b1010011 )
1$
#4350000000000
0$
#4375000000000
b1010100 )
b1010101 .
1$
#4400000000000
0$
#4425000000000
b1010110 .
b1010101 )
1$
#4450000000000
0$
#4475000000000
b1010110 )
b1010111 .
1$
#4500000000000
0$
#4525000000000
b1011000 .
b1010111 )
1$
#4550000000000
0$
#4575000000000
b1011000 )
b1011001 .
1$
#4600000000000
0$
#4625000000000
b1011010 .
b1011001 )
1$
#4650000000000
0$
#4675000000000
b1011010 )
b1011011 .
1$
#4700000000000
0$
#4725000000000
b1011100 .
b1011011 )
1$
#4750000000000
0$
#4775000000000
b1011100 )
b1011101 .
1$
#4800000000000
0$
#4825000000000
b1011110 .
b1011101 )
1$
#4850000000000
0$
#4875000000000
b1011110 )
b1011111 .
1$
#4900000000000
0$
#4925000000000
b1100000 .
b1011111 )
1$
#4950000000000
0$
#4975000000000
b1100000 )
b1100001 .
1$
#5000000000000
0$
#5025000000000
b1100010 .
b1100001 )
1$
#5050000000000
0$
#5075000000000
b1100010 )
b1100011 .
1$
#5100000000000
0$
#5125000000000
b1100100 .
b1100011 )
1$
#5150000000000
0$
#5175000000000
b1100100 )
b1100101 .
1$
#5200000000000
0$
#5225000000000
b1100110 .
b1100101 )
1$
#5250000000000
0$
#5275000000000
b1100110 )
b1100111 .
1$
#5300000000000
0$
#5325000000000
b1101000 .
b1100111 )
1$
#5350000000000
0$
#5375000000000
b1101000 )
b1101001 .
1$
#5400000000000
0$
#5425000000000
b1101010 .
b1101001 )
1$
#5450000000000
0$
#5475000000000
b1101010 )
b1101011 .
1$
#5500000000000
0$
#5525000000000
b1101100 .
b1101011 )
1$
#5550000000000
0$
#5575000000000
b1101100 )
b1101101 .
1$
#5600000000000
0$
#5625000000000
b1101110 .
b1101101 )
1$
#5650000000000
0$
#5675000000000
b1101110 )
b1101111 .
1$
#5700000000000
0$
#5725000000000
b1110000 .
b1101111 )
1$
#5750000000000
0$
#5775000000000
b1110000 )
b1110001 .
1$
#5800000000000
0$
#5825000000000
b1110010 .
b1110001 )
1$
#5850000000000
0$
#5875000000000
b1110010 )
b1110011 .
1$
#5900000000000
0$
#5925000000000
b1110100 .
b1110011 )
1$
#5950000000000
0$
#5975000000000
b1110100 )
b1110101 .
1$
#6000000000000
0$
#6025000000000
b1110110 .
b1110101 )
1$
#6050000000000
0$
#6075000000000
b1110110 )
b1110111 .
1$
#6100000000000
0$
#6125000000000
b1111000 .
b1110111 )
1$
#6150000000000
0$
#6175000000000
b1111000 )
b1111001 .
1$
#6200000000000
0$
#6225000000000
b1111010 .
b1111001 )
1$
#6250000000000
0$
#6275000000000
b1111010 )
b1111011 .
1$
#6300000000000
0$
#6325000000000
b1111100 .
b1111011 )
1$
#6350000000000
0$
#6375000000000
b1111100 )
b1111101 .
1$
#6400000000000
0$
#6425000000000
b1111110 .
b1111101 )
1$
#6450000000000
0$
#6475000000000
b1111110 )
b1111111 .
1$
#6500000000000
0$
#6525000000000
b10000000 .
b1111111 )
1$
#6550000000000
0$
#6575000000000
b10000000 )
b10000001 .
1$
#6600000000000
0$
#6625000000000
b10000010 .
b10000001 )
1$
#6650000000000
0$
#6675000000000
b10000010 )
b10000011 .
1$
#6700000000000
0$
#6725000000000
b10000100 .
b10000011 )
1$
#6750000000000
0$
#6775000000000
b10000100 )
b10000101 .
1$
#6800000000000
0$
#6825000000000
b10000110 .
b10000101 )
1$
#6850000000000
0$
#6875000000000
b10000110 )
b10000111 .
1$
#6900000000000
0$
#6925000000000
b10001000 .
b10000111 )
1$
#6950000000000
0$
#6975000000000
b10001000 )
b10001001 .
1$
#7000000000000
0$
#7025000000000
b10001010 .
b10001001 )
1$
#7050000000000
0$
#7075000000000
b10001010 )
b10001011 .
1$
#7100000000000
0$
#7125000000000
b10001100 .
b10001011 )
1$
#7150000000000
0$
#7175000000000
b10001100 )
b10001101 .
1$
#7200000000000
0$
#7225000000000
b10001110 .
b10001101 )
1$
#7250000000000
0$
#7275000000000
b10001110 )
b10001111 .
1$
#7300000000000
0$
#7325000000000
b10010000 .
b10001111 )
1$
#7350000000000
0$
#7375000000000
b10010000 )
b10010001 .
1$
#7400000000000
0$
#7425000000000
b10010010 .
b10010001 )
1$
#7450000000000
0$
#7475000000000
b10010010 )
b10010011 .
1$
#7500000000000
0$
#7525000000000
b10010100 .
b10010011 )
1$
#7550000000000
0$
#7575000000000
b10010100 )
b10010101 .
1$
#7600000000000
0$
#7625000000000
b10010110 .
b10010101 )
1$
#7650000000000
0$
#7675000000000
b10010110 )
b10010111 .
1$
#7700000000000
0$
#7725000000000
b10011000 .
b10010111 )
1$
#7750000000000
0$
#7775000000000
b10011000 )
b10011001 .
1$
#7800000000000
0$
#7825000000000
b10011010 .
b10011001 )
1$
#7850000000000
0$
#7875000000000
b10011010 )
b10011011 .
1$
#7900000000000
0$
#7925000000000
b10011100 .
b10011011 )
1$
#7950000000000
0$
#7975000000000
b10011100 )
b10011101 .
1$
#8000000000000
0$
#8025000000000
b10011110 .
b10011101 )
1$
#8050000000000
0$
#8075000000000
b10011110 )
b10011111 .
1$
#8100000000000
0$
#8125000000000
b10100000 .
b10011111 )
1$
#8150000000000
0$
#8175000000000
b10100000 )
b10100001 .
1$
#8200000000000
0$
#8225000000000
b10100010 .
b10100001 )
1$
#8250000000000
0$
#8275000000000
b10100010 )
b10100011 .
1$
#8300000000000
0$
#8325000000000
b10100100 .
b0 )
b10 +
1$
#8350000000000
0$
#8375000000000
b1 )
b10100101 .
1$
#8400000000000
0$
#8425000000000
b10100110 .
b10 )
1$
#8450000000000
0$
#8475000000000
b11 )
b10100111 .
1$
#8500000000000
0$
#8525000000000
b10101000 .
b100 )
1$
#8550000000000
0$
#8575000000000
b101 )
b10101001 .
1$
#8600000000000
0$
#8625000000000
b10101010 .
b110 )
1$
#8650000000000
0$
#8675000000000
b111 )
b10101011 .
1$
#8700000000000
0$
#8725000000000
b10101100 .
b1000 )
1$
#8750000000000
0$
#8775000000000
b1001 )
b10101101 .
1$
#8800000000000
0$
#8825000000000
b10101110 .
b1010 )
1$
#8850000000000
0$
#8875000000000
b1011 )
b10101111 .
1$
#8900000000000
0$
#8925000000000
b10110000 .
b1100 )
1$
#8950000000000
0$
#8975000000000
b1101 )
b10110001 .
1$
#9000000000000
0$
#9025000000000
b10110010 .
b1110 )
1$
#9050000000000
0$
#9075000000000
b1111 )
b10110011 .
1$
#9100000000000
0$
#9125000000000
b10110100 .
b10000 )
1$
#9150000000000
0$
#9175000000000
b10001 )
b10110101 .
1$
#9200000000000
0$
#9225000000000
b10110110 .
b10010 )
1$
#9250000000000
0$
#9275000000000
b10011 )
b10110111 .
1$
#9300000000000
0$
#9325000000000
b10111000 .
b10100 )
1$
#9350000000000
0$
#9375000000000
b10101 )
b10111001 .
1$
#9400000000000
0$
#9425000000000
b10111010 .
b10110 )
1$
#9450000000000
0$
#9475000000000
b10111 )
b10111011 .
1$
#9500000000000
0$
#9525000000000
b10111100 .
b11000 )
1$
#9550000000000
0$
#9575000000000
b11001 )
b10111101 .
1$
#9600000000000
0$
#9625000000000
b10111110 .
b11010 )
1$
#9650000000000
0$
#9675000000000
b11011 )
b10111111 .
1$
#9700000000000
0$
#9725000000000
b11000000 .
b11100 )
1$
#9750000000000
0$
#9775000000000
b11101 )
b11000001 .
1$
#9800000000000
0$
#9825000000000
b11000010 .
b11110 )
1$
#9850000000000
0$
#9875000000000
b11111 )
b11000011 .
1$
#9900000000000
0$
#9925000000000
b11000100 .
b100000 )
1$
#9950000000000
0$
#9975000000000
b100001 )
b11000101 .
1$
#10000000000000
0$
#10025000000000
b11000110 .
b100010 )
1$
#10050000000000
0$
#10075000000000
b100011 )
b11000111 .
1$
#10100000000000
0$
#10125000000000
b11001000 .
b100100 )
1$
#10150000000000
0$
#10175000000000
b100101 )
b11001001 .
1$
#10200000000000
0$
#10225000000000
b11001010 .
b100110 )
1$
#10250000000000
0$
#10275000000000
b100111 )
b11001011 .
1$
#10300000000000
0$
#10325000000000
b11001100 .
b101000 )
1$
#10350000000000
0$
#10375000000000
b101001 )
b11001101 .
1$
#10400000000000
0$
#10425000000000
b11001110 .
b101010 )
1$
#10450000000000
0$
#10475000000000
b101011 )
b11001111 .
1$
#10500000000000
0$
#10525000000000
b11010000 .
b101100 )
1$
#10550000000000
0$
#10575000000000
b101101 )
b11010001 .
1$
#10600000000000
0$
#10625000000000
b11010010 .
b101110 )
1$
#10650000000000
0$
#10675000000000
b101111 )
b11010011 .
1$
#10700000000000
0$
#10725000000000
b11010100 .
b110000 )
1$
#10750000000000
0$
#10775000000000
b110001 )
b11010101 .
1$
#10800000000000
0$
#10825000000000
b11010110 .
b110010 )
1$
#10850000000000
0$
#10875000000000
b110011 )
b11010111 .
1$
#10900000000000
0$
#10925000000000
b11011000 .
b110100 )
1$
#10950000000000
0$
#10975000000000
b110101 )
b11011001 .
1$
#11000000000000
0$
#11025000000000
b11011010 .
b110110 )
1$
#11050000000000
0$
#11075000000000
b110111 )
b11011011 .
1$
#11100000000000
0$
#11125000000000
b11011100 .
b111000 )
1$
#11150000000000
0$
#11175000000000
b111001 )
b11011101 .
1$
#11200000000000
0$
#11225000000000
b11011110 .
b111010 )
1$
#11250000000000
0$
#11275000000000
b111011 )
b11011111 .
1$
#11300000000000
0$
#11325000000000
b11100000 .
b111100 )
1$
#11350000000000
0$
#11375000000000
b111101 )
b11100001 .
1$
#11400000000000
0$
#11425000000000
b11100010 .
b111110 )
1$
#11450000000000
0$
#11475000000000
b111111 )
b11100011 .
1$
#11500000000000
0$
#11525000000000
b11100100 .
b1000000 )
1$
#11550000000000
0$
#11575000000000
b1000001 )
b11100101 .
1$
#11600000000000
0$
#11625000000000
b11100110 .
b1000010 )
1$
#11650000000000
0$
#11675000000000
b1000011 )
b11100111 .
1$
#11700000000000
0$
#11725000000000
b11101000 .
b1000100 )
1$
#11750000000000
0$
#11775000000000
b1000101 )
b11101001 .
1$
#11800000000000
0$
#11825000000000
b11101010 .
b1000110 )
1$
#11850000000000
0$
#11875000000000
b1000111 )
b11101011 .
1$
#11900000000000
0$
#11925000000000
b11101100 .
b1001000 )
1$
#11950000000000
0$
#11975000000000
b1001001 )
b11101101 .
1$
#12000000000000
0$
#12025000000000
b11101110 .
b1001010 )
1$
#12050000000000
0$
#12075000000000
b1001011 )
b11101111 .
1$
#12100000000000
0$
#12125000000000
b11110000 .
b1001100 )
1$
#12150000000000
0$
#12175000000000
b1001101 )
b11110001 .
1$
#12200000000000
0$
#12225000000000
b11110010 .
b1001110 )
1$
#12250000000000
0$
#12275000000000
b1001111 )
b11110011 .
1$
#12300000000000
0$
#12325000000000
b11110100 .
b1010000 )
1$
#12350000000000
0$
#12375000000000
b1010001 )
b11110101 .
1$
#12400000000000
0$
#12425000000000
b11110110 .
b1010010 )
1$
#12450000000000
0$
#12475000000000
b1010011 )
b11110111 .
1$
#12500000000000
0$
#12525000000000
b11111000 .
b1010100 )
1$
#12550000000000
0$
#12575000000000
b1010101 )
b11111001 .
1$
#12600000000000
0$
#12625000000000
b11111010 .
b1010110 )
1$
#12650000000000
0$
#12675000000000
b1010111 )
b11111011 .
1$
#12700000000000
0$
#12725000000000
b11111100 .
b1011000 )
1$
#12750000000000
0$
#12775000000000
b1011001 )
b11111101 .
1$
#12800000000000
0$
#12825000000000
b11111110 .
b1011010 )
1$
#12850000000000
0$
#12875000000000
b1011011 )
b11111111 .
1$
#12900000000000
0$
#12925000000000
b100000000 .
b1011100 )
1$
#12950000000000
0$
#12975000000000
b1011101 )
b100000001 .
1$
#13000000000000
0$
#13025000000000
b100000010 .
b1011110 )
1$
#13050000000000
0$
#13075000000000
b1011111 )
b100000011 .
1$
#13100000000000
0$
#13125000000000
b100000100 .
b1100000 )
1$
#13150000000000
0$
#13175000000000
b1100001 )
b100000101 .
1$
#13200000000000
0$
#13225000000000
b100000110 .
b1100010 )
1$
#13250000000000
0$
#13275000000000
b1100011 )
b100000111 .
1$
#13300000000000
0$
#13325000000000
b100001000 .
b1100100 )
1$
#13350000000000
0$
#13375000000000
b1100101 )
b100001001 .
1$
#13400000000000
0$
#13425000000000
b100001010 .
b1100110 )
1$
#13450000000000
0$
#13475000000000
b1100111 )
b100001011 .
1$
#13500000000000
0$
#13525000000000
b100001100 .
b1101000 )
1$
#13550000000000
0$
#13575000000000
b1101001 )
b100001101 .
1$
#13600000000000
0$
#13625000000000
b100001110 .
b1101010 )
1$
#13650000000000
0$
#13675000000000
b1101011 )
b100001111 .
1$
#13700000000000
0$
#13725000000000
b100010000 .
b1101100 )
1$
#13750000000000
0$
#13775000000000
b1101101 )
b100010001 .
1$
#13800000000000
0$
#13825000000000
b100010010 .
b1101110 )
1$
#13850000000000
0$
#13875000000000
b1101111 )
b100010011 .
1$
#13900000000000
0$
#13925000000000
b100010100 .
b1110000 )
1$
#13950000000000
0$
#13975000000000
b1110001 )
b100010101 .
1$
#14000000000000
0$
#14025000000000
b100010110 .
b1110010 )
1$
#14050000000000
0$
#14075000000000
b1110011 )
b100010111 .
1$
#14100000000000
0$
#14125000000000
b100011000 .
b1110100 )
1$
#14150000000000
0$
#14175000000000
b1110101 )
b100011001 .
1$
#14200000000000
0$
#14225000000000
b100011010 .
b1110110 )
1$
#14250000000000
0$
#14275000000000
b1110111 )
b100011011 .
1$
#14300000000000
0$
#14325000000000
b100011100 .
b1111000 )
1$
#14350000000000
0$
#14375000000000
b1111001 )
b100011101 .
1$
#14400000000000
0$
#14425000000000
b100011110 .
b1111010 )
1$
#14450000000000
0$
#14475000000000
b1111011 )
b100011111 .
1$
#14500000000000
0$
#14525000000000
b100100000 .
b1111100 )
1$
#14550000000000
0$
#14575000000000
b1111101 )
b100100001 .
1$
#14600000000000
0$
#14625000000000
b100100010 .
b1111110 )
1$
#14650000000000
0$
#14675000000000
b1111111 )
b100100011 .
1$
#14700000000000
0$
#14725000000000
b100100100 .
b10000000 )
1$
#14750000000000
0$
#14775000000000
b10000001 )
b100100101 .
1$
#14800000000000
0$
#14825000000000
b100100110 .
b10000010 )
1$
#14850000000000
0$
#14875000000000
b10000011 )
b100100111 .
1$
#14900000000000
0$
#14925000000000
b100101000 .
b10000100 )
1$
#14950000000000
0$
#14975000000000
b10000101 )
b100101001 .
1$
#15000000000000
0$
#15025000000000
b100101010 .
b10000110 )
1$
#15050000000000
0$
#15075000000000
b10000111 )
b100101011 .
1$
#15100000000000
0$
#15125000000000
b100101100 .
b10001000 )
1$
#15150000000000
0$
#15175000000000
b10001001 )
b100101101 .
1$
#15200000000000
0$
#15225000000000
b100101110 .
b10001010 )
1$
#15250000000000
0$
#15275000000000
b10001011 )
b100101111 .
1$
#15300000000000
0$
#15325000000000
b100110000 .
b10001100 )
1$
#15350000000000
0$
#15375000000000
b10001101 )
b100110001 .
1$
#15400000000000
0$
#15425000000000
b100110010 .
b10001110 )
1$
#15450000000000
0$
#15475000000000
b10001111 )
b100110011 .
1$
#15500000000000
0$
#15525000000000
b100110100 .
b10010000 )
1$
#15550000000000
0$
#15575000000000
b10010001 )
b100110101 .
1$
#15600000000000
0$
#15625000000000
b100110110 .
b10010010 )
1$
#15650000000000
0$
#15675000000000
b10010011 )
b100110111 .
1$
#15700000000000
0$
#15725000000000
b100111000 .
b10010100 )
1$
#15750000000000
0$
#15775000000000
b10010101 )
b100111001 .
1$
#15800000000000
0$
#15825000000000
b100111010 .
b10010110 )
1$
#15850000000000
0$
#15875000000000
b10010111 )
b100111011 .
1$
#15900000000000
0$
#15925000000000
b100111100 .
b10011000 )
1$
#15950000000000
0$
#15975000000000
b10011001 )
b100111101 .
1$
#16000000000000
0$
#16025000000000
b100111110 .
b10011010 )
1$
#16050000000000
0$
#16075000000000
b10011011 )
b100111111 .
1$
#16100000000000
0$
#16125000000000
b101000000 .
b10011100 )
1$
#16150000000000
0$
#16175000000000
b10011101 )
b101000001 .
1$
#16200000000000
0$
#16225000000000
b101000010 .
b10011110 )
1$
#16250000000000
0$
#16275000000000
b10011111 )
b101000011 .
1$
#16300000000000
0$
#16325000000000
b101000100 .
b10100000 )
1$
#16350000000000
0$
#16375000000000
b10100001 )
b101000101 .
1$
#16400000000000
0$
#16425000000000
b10 1
b0 .
b10100010 )
1$
#16450000000000
0$
#16475000000000
b10100011 )
b1 .
1"
1$
#16500000000000
0$
#16525000000000
b10 .
b10100100 )
1$
#16550000000000
0$
#16575000000000
b10100101 )
b11 .
1$
#16600000000000
0$
#16625000000000
b100 .
b10100110 )
1$
#16650000000000
0$
#16675000000000
b10100111 )
b101 .
1$
#16700000000000
0$
#16725000000000
b110 .
b10101000 )
1$
#16750000000000
0$
#16775000000000
b10101001 )
b111 .
1$
#16800000000000
0$
#16825000000000
b1000 .
b10101010 )
1$
#16850000000000
0$
#16875000000000
b10101011 )
b1001 .
1$
#16900000000000
0$
#16925000000000
b1010 .
b10101100 )
1$
#16950000000000
0$
#16975000000000
b10101101 )
b1011 .
1$
#17000000000000
0$
#17025000000000
b1100 .
b10101110 )
1$
#17050000000000
0$
