04/ethernet/phy_tx.v
module phy_tx(
    input   wire        in_txen,
    input   wire [7:0]  in_txd,
    output  wire        out_txc,
    output  wire        out_txen,
    output  wire [7:0]  out_txd
    );

    reg clock;
    reg r_txen;
    reg [7:0] r_txd;

    assign out_txc = clock;
    assign out_txen = r_txen;
    assign out_txd = r_txd;

    initial begin
        clock <= 0;
    end

    always begin
        #10 clock = ~clock;
        r_txen <= in_txen;
        r_txd <= in_txd;
    end

endmodule

04/ethernet/phy_rx.v
// The PHY receives data from the wire and transmits it to the MAC. This module handles this signal
// along with generating the receive clock which is an output of the PHY.
module phy_rx(
    input   wire        in_rxen,
    input   wire [7:0]  in_rxd,
    output  wire        out_rxc,
    output  wire        out_rxdv,
    output  wire [7:0]  out_rxd,
    output  wire        out_rxer,
    output  wire        out_crs
    );

    reg r_clk;



endmodule

04/ethernet/phy.v
`include "phy_tx.v"
`include "phy_rx.v"

// The Ethernet PHY is a component that operates at the physical layer of the OSI network model.
// It implements the physical layer portion of the Ethernet. Its purpose is to provide analog signal
// physical access to the link. It is usually interfaced with a media-independent interface (MII)
// to a MAC chip in a microcontroller or another system that takes care of the higher layer functions.
//
// More specifically, the Ethernet PHY is a chip that implements the hardware send and receive function
// of Ethernet frames; it interfaces between the analog domain of Ethernet's line modulation and the
// digital domain of link-layer packet signaling. The PHY usually does not handle MAC addressing,
// as that is the link layer's job. Similarly, Wake-on-LAN and Boot ROM functionality is implemented
// in the network interface card (NIC), which may have PHY, MAC, and other functionality integrated
// into one chip or as separate chips.
//
// https://en.wikipedia.org/wiki/Physical_layer#PHY
module phy(
    input   wire        in_txen,    // mii/mac to phy transmit enable
    input   wire [7:0]  in_txd,     // mii/mac to phy transmit data
    input   wire        in_rxen,    // wire to phy receive enable
    input   wire [7:0]  in_rxd,     // wire to phy receive data
    output  wire        out_txc,    // transmit clock (phy to mii/mac)
    output  wire        out_txen,   // phy to wire transmit enable
    output  wire [7:0]  out_txd,    // phy to wire transmit data
    output  wire        out_rxc,    // receive clock (phy to mac/mii)
    output  wire        out_rxdv,   // phy to mii/mac receive data valid
    output  wire [7:0]  out_rxd,    // phy to mii/mac receive data
    output  wire        out_rxer,   // phy to mii/mac receiver err
    output  wire        out_crs     // phy to mii/mac carrier sense
    );

    // Receive data from analog wire and output to mii
    phy_rx phy_rx(in_rxen, in_rxd, out_rxc, out_rxdv, out_rxd, our_rxer, out_crs);

    // Transmit data from Mii to analog wire
    phy_tx phy_tx(in_txen, in_txd, out_txc, out_txen, out_txd);

endmodule

04/ethernet/mac_tx.v
// Receives payload data from higher layers of the OSI model. Packages it into
// an ethernet frame and transmits it to the MII which then passes it on to
// the PHY.
module mac_tx(
    input   wire            in_clk,
    input   wire            in_txen,
    input   wire [7:0]      in_txd,
    output  wire            out_tx_ready,   // tell the higher layer to send or stop sending data
    output  wire            out_txen,
    output  wire [7:0]      out_txd
    );

    reg                     r_tx_ready;     // 1 when we're sending payload, 0 in all other cases
    reg                     r_txen;
    reg [7:0]               r_txd;
    reg [55:0]              r_preamble = 56'b10101010_10101010_10101010_10101010_10101010_10101010_10101010;
    reg [7:0]               r_sfd;        // start frame delimiter
    reg [47:0]              r_dest_mac;
    reg [47:0]              r_src_mac;
    reg [15:0]              r_ether_type;
    reg [7:0]               r_payload;    // min is 46 octets and max is 1500 octets
    reg [31:0]              r_fcs;        // frame check sequence
    reg [95:0]              r_ipg;        // inter packet gap
    reg [3:0]               r_stage;
    reg [7:0]               r_data;
    reg [23:0]              r_offset;

    `define IDLE            4'd0
    `define PREAMBLE        4'd1
    `define SFD             4'd2
    `define MACDEST         4'd3
    `define MACSRC          4'd4
    `define ETHERTYPE       4'd5
    `define PAYLOAD         4'd6
    `define FCS             4'd7
    `define IPG             4'd8

    assign out_tx_ready = r_tx_ready;
    assign out_txen = r_txen;
    assign out_txd = r_data;

    initial begin
        r_data <= 8'd0;
        r_data[0] <= 0;
        r_txen = 0;
        r_tx_ready = 1;
        r_dest_mac <= 48'd0; // TODO
        r_src_mac <= 48'd0; // TODO
        r_ether_type <= 16'd0; // TODO
        // r_preamble <= 56'b10101010_10101010_10101010_10101010_10101010_10101010_10101010;
        r_sfd <= 8'b10101011;
        r_ipg <= 96'd0;
        r_stage <= 4'd0;
        r_offset <= 0;
    end

    always @(posedge in_clk) begin
        if (in_txen) begin
            if (r_stage == `IDLE)
                r_stage = `PREAMBLE;

            case (r_stage)
                `PREAMBLE: begin
                    r_txen <= 1;
                    r_tx_ready <= 0;
                    // r_data = 8'd0;
                    r_data <= r_preamble[(6-r_offset)*8 +: 8];
                    $display("val is %b", r_preamble[(6-r_offset)*8 +: 8]);
                    r_offset += 1;
                    if (r_offset >= 7) begin
                        r_offset <= 0;
                        r_stage <= `SFD;
                    end
                end

                `SFD: begin
                    r_txen <= 1;
                    r_tx_ready <= 0;
                    r_data <= r_sfd;
                    r_stage <= `MACDEST;
                end

                `MACDEST: begin
                    r_txen <= 1;
                    r_tx_ready <= 0;
                    r_data <= r_dest_mac[(5-r_offset)*8 +: 8];
                    r_offset += 1;
                    if (r_offset >= 6) begin
                        r_offset <= 0;
                        r_stage <= `MACSRC;
                    end
                end

                `MACSRC: begin
                    r_txen <= 1;
                    r_tx_ready <= 0;
                    r_data <= r_src_mac[(5-r_offset)*8 +: 8];
                    r_offset += 1;
                    if (r_offset >= 6) begin
                        r_offset <= 0;
                        r_stage <= `ETHERTYPE;
                    end
                end

                `ETHERTYPE: begin
                    r_txen <= 1;
                    r_tx_ready <= 0;
                    r_data <= r_ether_type[(1-r_offset)*8 +: 8];
                    r_offset += 1;
                    if (r_offset >= 2) begin
                        r_offset <= 0;
                        r_stage <= `PAYLOAD;
                    end
                end

                `PAYLOAD: begin
                    r_txen <= 1;
                    r_tx_ready <= 1;
                    r_data <= in_txd;
                end

                default: begin
                    $finish;
                end
            endcase
        end else begin // in_txen = 0
            case (r_stage)
                // We've received a 0 for txen, which means the payload has ended.
                `PAYLOAD: begin
                    r_txen <= 1;
                    r_tx_ready <= 1;
                    r_stage <= `IPG;
                end

                `IPG: begin
                    r_txen <= 1;
                    r_tx_ready <= 0;
                    r_data <= r_ipg[(11-r_offset)*8 +: 8];
                    r_offset += 1;
                    if (r_offset >= 12) begin
                        r_data <= 8'd0;
                        r_txen <= 0;
                        r_stage <= `IDLE;
                    end
                end

                default: begin
                    r_stage <= `IDLE;
                    r_txen <= 0;
                    r_tx_ready <= 1;
                end
            endcase
        end
    end

    // always @(posedge in_clk) begin
    //     r_txd <= r_data;
    // end

endmodule

04/ethernet/mac.v
`include "mac_rx.v"
`include "mac_tx.v"

// The MAC sublayer provides a control abstraction of the physical layer such that the complexities
// of physical link control are invisible to the LLC and upper layers of the network stack. Thus any
// LLC sublayer (and higher layers) may be used with any MAC. In turn, the medium access control block
// is formally connected to the PHY via a media-independent interface.
//
// When sending data to another device on the network, the MAC sublayer encapsulates higher-level
// frames into frames appropriate for the transmission medium (i.e. the MAC adds a syncword preamble
// and also padding if necessary), adds a frame check sequence to identify transmission errors, and
// then forwards the data to the physical layer as soon as the appropriate channel access method permits it.
//
// When receiving data from the physical layer, the MAC block ensures data integrity by verifying the
// sender's frame check sequences, and strips off the sender's preamble and padding before passing
// the data up to the higher layers.
//
// https://en.wikipedia.org/wiki/Medium_access_control
module mac(
    input   wire        in_txc,         // transmit clock (higher layer to mac)
    input   wire        in_txen,        // higher layer to mac transmit enable
    input   wire [7:0]  in_txd,         // higher layer to mac transmit data
    input   wire        in_rxc,         // receive clock (mii/phy to mac)
    input   wire        in_rxdv,        // mii/phy to mac receive data valid
    input   wire [7:0]  in_rxd,         // mii/phy to mac receive data
    input   wire        in_rxer,        // mii/phy to mac receive err
    input   wire        in_crs,         // mii/phy to mac carrier sense
    output  wire        out_tx_ready,   // mac to higher layer signalling payload can be received
    output  wire        out_txen,       // mac to mii/phy transmit enable
    output  wire [7:0]  out_txd         // mac to mii/phy transmit data
    );

    // When data is received from the from the MII(PHY), we need to deconstruct the frame into it's
    // constituents for the MII to pass it forward to the data-link layer of the OSI model.
    // mac_rx mac_rx(in_rxc, in_rxdv, in_rxd, in_rxer, in_crs, out_txen, out_txd);

    // When data is received from the data-link layer of the OSI, we need to construct an ethernet
    // frame and pass it to the MII so that it can forward it to the PHY.
    mac_tx mac_tx(in_txc, in_txen, in_txd, out_tx_ready, out_txen, out_txd);

endmodule

04/ethernet/eth_controller.v
// Encapsulates: Data-link layer <-> MAC <-> MII <-> PHY <-> Wire
// Inputs/Outputs:
// - Higher layer
// - Wire
module eth_controller(
    input   wire          in_txen,      // mcu/cpu transmit enable
    input   wire [7:0]    in_txd,       // mcu/cpu transmit data
    input   wire          in_rxen,      // wire receive enable
    input   wire [7:0]    in_rxd,       // wire receive data
    output  wire          out_tx_ready, // mcu/cpu transmit ready (1 after preamble etc has been sent)
    output  wire          out_wire_txen,// phy to wire transmit enable
    output  wire [7:0]    out_wire_txd, // phy to wire transmit data
    );

    // We've included the MII in this module itself. It is essentially common wires between the MAC
    // and PHY. Since we're instantiating them here, it makes sense to connect them here to.
    //
    // The media-independent interface (MII) is a standard interface to connect a Ethernet media access 
    // control (MAC) block to a PHY chip.
    // The original MII transfers network data using 4-bit nibbles in each direction (4 transmit data 
    // bits, 4 receive data bits). The data is clocked at 25 MHz to achieve 100 Mbit/s throughput.
    // https://en.wikipedia.org/wiki/Media-independent_interface
    //
    // The transmit clock is a free-running clock generated by the PHY based on the link speed
    // (25 MHz for 100 Mbit/s, 2.5 MHz for 10 Mbit/s).
    // The remaining transmit signals are driven by the MAC synchronously on the rising edge of TXC.
    // This arrangement allows the MAC to operate without having to be aware of the link speed.
    // The transmit enable signal is held high during frame transmission and low when the transmitter
    // is idle.
    wire        w_txc;      // transmit clock
    wire        w_txen;     // transmit enable
    wire [7:0]  w_txd;      // transmit data

    // The first seven receiver signals are entirely analogous to the transmitter signals, except
    // RX_ER is not optional and used to indicate the received signal could not be decoded to valid
    // data. The receive clock is recovered from the incoming signal during frame reception. When
    // no clock can be recovered (i.e. when the medium is silent), the PHY must present a free-running
    // clock as a substitute.
    wire        w_rxc;      // receive clock
    wire        w_rxdv;     // receive data valid
    wire [7:0]  w_rxd;      // receive data
    wire        w_rxer;     // receive error
    wire        w_crs;      // carrier sense

    mac mac(
        .in_txc(w_txc),
        .in_txen(in_txen),
        .in_txd(in_txd),
        .in_rxc(w_rxc),
        .in_rxdv(w_rxdv),
        .in_rxd(w_rxd),
        .in_rxer(w_rxer),
        .in_crs(w_crs),
        .out_tx_ready(out_tx_ready),
        .out_txen(w_txen),
        .out_txd(w_txd)
    );

    phy phy(
        .in_txen(w_txen),
        .in_txd(w_txd),
        .in_rxen(in_rxen),
        .in_rxd(in_rxd),
        .out_txc(w_txc),
        .out_txen(out_wire_txen),
        .out_txd(out_wire_txd),
        .out_rxc(w_rxc),
        .out_rxdv(w_rxdv),
        .out_rxd(w_rxd),
        .out_rxer(w_rxer),
        .out_crs(w_crs)
    );

endmodule

04/ethernet/tb.v
`include "eth_controller.v"

module tb;
    wire          in_txen;      // mcu/cpu transmit enable
    wire [7:0]    in_txd;       // mcu/cpu transmit data
    wire          in_rxen;      // wire receive enable
    wire [7:0]    in_rxd;       // wire receive data
    wire          out_tx_ready; // mcu/cpu transmit ready (1 after preamble etc has been sent)
    wire          out_wire_txen;// phy to wire transmit enable
    wire [7:0]    out_wire_txd; // phy to wire transmit data

    reg clock;
    reg [23:0] r_offset;
    reg r_txen;
    reg [7:0] r_txd;
    reg [159:0] r_input_data;

    assign in_txen = r_txen;
    assign in_txd = r_txd;

    eth_controller eth_controller(
        .in_txen(in_txen),
        .in_txd(in_txd),
        .in_rxen(in_rxen),
        .in_rxd(in_rxd),
        .out_tx_ready(out_tx_ready),
        .out_wire_txen(out_wire_txen),
        .out_wire_txd(out_wire_txd)
    );

    initial begin
        $dumpfile("tb.vcd");
        $dumpvars;
    end

    initial begin
        clock = 0;
        r_offset = 0;
        r_txen = 0;
        r_input_data = 160'h00_01_02_03_04_05_06_07_08_09_0a_0b_0c_0d_0e_0f_10_11_12_13;
    end

    always begin
        #10 clock = ~clock;
    end

    always @(posedge clock) begin
        r_txen = 1;
        if (out_tx_ready) begin
            r_txd = r_input_data[(19-r_offset) * 8 +: 8];
            r_offset += 1;

            $display("Packet is %h", r_txd);

            if (r_offset >= 9)
                $finish;

        end else begin
            // r_txen = 0;
        end
    end

endmodule

04/ethernet/mac_rx.v
// When data is received from the from the PHY, we need to deconstruct the frame into it's 
// constituents for the MII to pass it forward
module mac_rx(
    input  wire          in_rxc,
    input  wire          in_rxdv,    // receive data valid
    input  wire [7:0]    in_rxd,     // receive data
    input  wire          in_rxer,    // receive error
    input  wire          in_crs,     // carrier sense
    output wire          out_txen,   // transmit enable
    output wire [7:0]    out_txd     // transmit data
    );


    reg                     r_txen;
    reg                     r_txd;
    reg [55:0]              r_preamble;
    reg [7:0]               r_sfd;        // start frame delimiter
    reg [47:0]              r_dest_mac;
    reg [47:0]              r_src_mac;
    reg [15:0]              r_ether_type;
    reg [7:0]               r_payload;    // min is 46 octets and max is 1500 octets
    reg [31:0]              r_fcs;        // frame check sequence
    reg [95:0]              r_igp;        // inter packet gap
    reg [3:0]               r_stage;
    reg [7:0]               r_data;
    reg [11:0]              r_offset;

    `define IDLE            4'd0
    `define PREAMBLE        4'd1
    `define SFD             4'd2
    `define MACDEST         4'd3
    `define MACSRC          4'd4
    `define ETHERTYPE       4'd5
    `define PAYLOAD         4'd6
    `define FCS             4'd7
    `define IGP             4'd8

    initial begin
        r_stage = `IDLE;
        r_offset = 12'd0;
    end

    assign out_txen = r_txen;
    assign out_txd = r_txd;

    always @(posedge in_rxc) begin
        if (in_crs) begin
            if (r_stage == `IDLE)
                r_stage = `PREAMBLE;

            case (r_stage)
                `IDLE: begin
                    r_txen = 1'b0;
                    r_offset = 12'd0;
                end

                `PREAMBLE: begin
                    r_txen = 1'b0;
                    r_preamble[(6-r_offset)*8 +: 8] = in_rxd;
                    r_offset += 12'd1;
                    if (r_offset == 12'd7) begin
                        if (r_preamble != 56'b10101010_10101010_10101010_10101010_10101010_10101010_10101010)
                            $finish;
                        r_offset = 12'd0;
                        r_stage = `SFD;
                    end
                end

                `SFD: begin
                    r_txen = 1'b0;
                    r_sfd = in_rxd;
                    r_offset += 12'd1;
                    if (r_offset == 1) begin
                        r_offset = 12'd0;
                        r_stage = `MACDEST;
                    end
                end

                `MACDEST: begin
                    r_txen = 1'b0;
                    r_dest_mac[(5-r_offset)*8 +: 8] = in_rxd;
                    r_offset += 12'd1;
                    if (r_offset == 12'd6) begin
                        r_offset = 12'd0;
                        r_stage = `MACSRC;
                    end
                end

                `MACSRC: begin
                    r_txen = 1'b0;
                    r_src_mac[(5-r_offset)*8 +: 8] = in_rxd;
                    r_offset += 12'd1;
                    if (r_offset == 12'd6) begin
                        r_offset = 12'd0;
                        r_stage = `ETHERTYPE;
                    end
                end

                `ETHERTYPE: begin
                    r_txen = 1'b1;
                    r_ether_type[(1-r_offset)*8 +: 8] = in_rxd;
                    r_offset += 12'd1;
                    if (r_offset == 12'd2) begin
                        r_offset = 12'd0;
                        r_stage = `PAYLOAD;
                    end
                end

                `PAYLOAD: begin
                end

                `IGP: begin
                end

            endcase

        end else begin
            r_stage = `IDLE;
            r_offset = 12'd0;
        end
    end

endmodule

04/ethernet/tb.vcd
$date
	Sun Jun 26 19:37:55 2022
$end
$version
	Icarus Verilog
$end
$timescale
	1s
$end
$scope module mac_rx $end
$var wire 1 ! in_crs $end
$var wire 1 " in_rxc $end
$var wire 8 # in_rxd [7:0] $end
$var wire 1 $ in_rxdv $end
$var wire 1 % in_rxer $end
$var wire 1 & out_txen $end
$var wire 8 ' out_txd [7:0] $end
$var reg 48 ( r_dest_mac [47:0] $end
$var reg 16 ) r_ether_type [15:0] $end
$var reg 12 * r_offset [11:0] $end
$var reg 56 + r_preamble [55:0] $end
$var reg 8 , r_sfd [7:0] $end
$var reg 48 - r_src_mac [47:0] $end
$var reg 4 . r_stage [3:0] $end
$var reg 1 / r_txd $end
$var reg 1 0 r_txen $end
$upscope $end
$scope module tb $end
$var wire 8 1 in_rxd [7:0] $end
$var wire 1 2 in_rxen $end
$var wire 8 3 in_txd [7:0] $end
$var wire 1 4 in_txen $end
$var wire 1 5 out_wire_txen $end
$var wire 8 6 out_wire_txd [7:0] $end
$var wire 1 7 out_tx_ready $end
$var reg 1 8 clock $end
$var reg 160 9 r_input_data [159:0] $end
$var reg 24 : r_offset [23:0] $end
$var reg 8 ; r_txd [7:0] $end
$var reg 1 < r_txen $end
$scope module eth_controller $end
$var wire 8 = in_rxd [7:0] $end
$var wire 1 2 in_rxen $end
$var wire 8 > in_txd [7:0] $end
$var wire 1 4 in_txen $end
$var wire 1 ? w_crs $end
$var wire 1 @ w_rxc $end
$var wire 8 A w_rxd [7:0] $end
$var wire 1 B w_rxdv $end
$var wire 1 C w_rxer $end
$var wire 1 D w_txen $end
$var wire 8 E w_txd [7:0] $end
$var wire 1 F w_txc $end
$var wire 1 5 out_wire_txen $end
$var wire 8 G out_wire_txd [7:0] $end
$var wire 1 7 out_tx_ready $end
$scope module mac $end
$var wire 1 ? in_crs $end
$var wire 1 @ in_rxc $end
$var wire 8 H in_rxd [7:0] $end
$var wire 1 B in_rxdv $end
$var wire 1 C in_rxer $end
$var wire 8 I in_txd [7:0] $end
$var wire 1 4 in_txen $end
$var wire 1 D out_txen $end
$var wire 8 J out_txd [7:0] $end
$var wire 1 7 out_tx_ready $end
$var wire 1 F in_txc $end
$scope module mac_tx $end
$var wire 8 K in_txd [7:0] $end
$var wire 1 4 in_txen $end
$var wire 1 7 out_tx_ready $end
$var wire 8 L out_txd [7:0] $end
$var wire 1 D out_txen $end
$var wire 1 F in_clk $end
$var reg 8 M r_data [7:0] $end
$var reg 48 N r_dest_mac [47:0] $end
$var reg 16 O r_ether_type [15:0] $end
$var reg 96 P r_ipg [95:0] $end
$var reg 24 Q r_offset [23:0] $end
$var reg 56 R r_preamble [55:0] $end
$var reg 8 S r_sfd [7:0] $end
$var reg 48 T r_src_mac [47:0] $end
$var reg 4 U r_stage [3:0] $end
$var reg 1 V r_tx_ready $end
$var reg 1 W r_txen $end
$upscope $end
$upscope $end
$scope module phy $end
$var wire 8 X in_rxd [7:0] $end
$var wire 1 2 in_rxen $end
$var wire 8 Y in_txd [7:0] $end
$var wire 1 D in_txen $end
$var wire 1 Z our_rxer $end
$var wire 1 ? out_crs $end
$var wire 1 @ out_rxc $end
$var wire 8 [ out_rxd [7:0] $end
$var wire 1 B out_rxdv $end
$var wire 1 C out_rxer $end
$var wire 1 5 out_txen $end
$var wire 8 \ out_txd [7:0] $end
$var wire 1 F out_txc $end
$scope module phy_rx $end
$var wire 8 ] in_rxd [7:0] $end
$var wire 1 2 in_rxen $end
$var wire 1 ? out_crs $end
$var wire 1 @ out_rxc $end
$var wire 8 ^ out_rxd [7:0] $end
$var wire 1 B out_rxdv $end
$var wire 1 Z out_rxer $end
$upscope $end
$scope module phy_tx $end
$var wire 8 _ in_txd [7:0] $end
$var wire 1 D in_txen $end
$var wire 1 F out_txc $end
$var wire 8 ` out_txd [7:0] $end
$var wire 1 5 out_txen $end
$var reg 1 a clock $end
$var reg 8 b r_txd [7:0] $end
$var reg 1 c r_txen $end
$upscope $end
$upscope $end
$upscope $end
$upscope $end
$enddefinitions $end
#0
$dumpvars
xc
bx b
0a
bx `
b0 _
bz ^
bz ]
bx \
bz [
zZ
b0 Y
bz X
0W
1V
b0 U
b0 T
b10101011 S
b10101010101010101010101010101010101010101010101010101010 R
b0 Q
b0 P
b0 O
b0 N
b0 M
b0 L
bx K
b0 J
bx I
bz H
bx G
0F
b0 E
0D
zC
zB
bz A
z@
z?
bx >
bz =
0<
bx ;
b0 :
b1000000100000001100000100000001010000011000000111000010000000100100001010000010110000110000001101000011100000111100010000000100010001001000010011 9
08
17
bx 6
x5
04
bx 3
z2
bz 1
x0
x/
b0 .
bx -
bx ,
bx +
b0 *
bx )
bx (
b0x '
x&
z%
z$
bz #
z"
z!
$end
#10
b0 6
b0 G
b0 \
b0 `
b0 b
05
0c
b1 :
b0 3
b0 >
b0 I
b0 K
b0 ;
14
1<
18
1F
1a
#20
08
0F
0a
#30
b10101010 E
b10101010 J
b10101010 L
b10101010 Y
b10101010 _
b10101010 M
07
0V
1D
1W
b10 :
b1 3
b1 >
b1 I
b1 K
b1 ;
b1 Q
b1 U
18
1F
1a
#40
b10101010 6
b10101010 G
b10101010 \
b10101010 `
b10101010 b
15
1c
08
0F
0a
#50
b10 Q
18
1F
1a
#60
08
0F
0a
#70
b11 Q
18
1F
1a
#80
08
0F
0a
#90
b100 Q
18
1F
1a
#100
08
0F
0a
#110
b101 Q
18
1F
1a
#120
08
0F
0a
#130
b110 Q
18
1F
1a
#140
08
0F
0a
#150
b10 U
b0 Q
18
1F
1a
#160
08
0F
0a
#170
b11 U
b10101011 E
b10101011 J
b10101011 L
b10101011 Y
b10101011 _
b10101011 M
18
1F
1a
#180
b10101011 6
b10101011 G
b10101011 \
b10101011 `
b10101011 b
08
0F
0a
#190
b0 E
b0 J
b0 L
b0 Y
b0 _
b0 M
b1 Q
18
1F
1a
#200
b0 6
b0 G
b0 \
b0 `
b0 b
08
0F
0a
#210
b10 Q
18
1F
1a
#220
08
0F
0a
#230
b11 Q
18
1F
1a
#240
08
0F
0a
#250
b100 Q
18
1F
1a
#260
08
0F
0a
#270
b101 Q
18
1F
1a
#280
08
0F
0a
#290
b100 U
b0 Q
18
1F
1a
#300
08
0F
0a
#310
b1 Q
18
1F
1a
#320
08
0F
0a
#330
b10 Q
18
1F
1a
#340
08
0F
0a
#350
b11 Q
18
1F
1a
#360
08
0F
0a
#370
b100 Q
18
1F
1a
#380
08
0F
0a
#390
b101 Q
18
1F
1a
#400
08
0F
0a
#410
b101 U
b0 Q
18
1F
1a
#420
08
0F
0a
#430
b1 Q
18
1F
1a
#440
08
0F
0a
#450
b110 U
b0 Q
18
1F
1a
#460
08
0F
0a
#470
b1 E
b1 J
b1 L
b1 Y
b1 _
b1 M
17
1V
18
1F
1a
#480
b1 6
b1 G
b1 \
b1 `
b1 b
08
0F
0a
#490
b11 :
b10 3
b10 >
b10 I
b10 K
b10 ;
18
1F
1a
#500
08
0F
0a
#510
b10 E
b10 J
b10 L
b10 Y
b10 _
b10 M
b100 :
b11 3
b11 >
b11 I
b11 K
b11 ;
18
1F
1a
#520
b10 6
b10 G
b10 \
b10 `
b10 b
08
0F
0a
#530
b11 E
b11 J
b11 L
b11 Y
b11 _
b11 M
b101 :
b100 3
b100 >
b100 I
b100 K
b100 ;
18
1F
1a
#540
b11 6
b11 G
b11 \
b11 `
b11 b
08
0F
0a
#550
b100 E
b100 J
b100 L
b100 Y
b100 _
b100 M
b110 :
b101 3
b101 >
b101 I
b101 K
b101 ;
18
1F
1a
#560
b100 6
b100 G
b100 \
b100 `
b100 b
08
0F
0a
#570
b101 E
b101 J
b101 L
b101 Y
b101 _
b101 M
b111 :
b110 3
b110 >
b110 I
b110 K
b110 ;
18
1F
1a
#580
b101 6
b101 G
b101 \
b101 `
b101 b
08
0F
0a
#590
b110 E
b110 J
b110 L
b110 Y
b110 _
b110 M
b1000 :
b111 3
b111 >
b111 I
b111 K
b111 ;
18
1F
1a
#600
b110 6
b110 G
b110 \
b110 `
b110 b
08
0F
0a
#610
b111 E
b111 J
b111 L
b111 Y
b111 _
b111 M
b1001 :
b1000 3
b1000 >
b1000 I
b1000 K
b1000 ;
18
1F
1a
