04/ethernet/mac_tx.v
// Receives payload data from higher layers of the OSI model. Packages it into
// an ethernet frame and transmits it to the MII which then passes it on to
// the PHY.
module mac_tx(
    input   wire            in_clk,
    input   wire            in_txen,
    input   wire [7:0]      in_txd,
    output  wire            out_tx_ready,   // tell the higher layer to send or stop sending data
    output  wire            out_txen,
    output  wire [7:0]      out_txd
    );

    reg                     r_tx_ready;     // 1 when we're sending payload, 0 in all other cases
    reg                     r_txen;
    reg [7:0]               r_txd;
    reg [55:0]              r_preamble;
    reg [7:0]               r_sfd;        // start frame delimiter
    reg [47:0]              r_dest_mac;
    reg [47:0]              r_src_mac;
    reg [15:0]              r_ether_type;
    reg [7:0]               r_payload;    // min is 46 octets and max is 1500 octets
    reg [31:0]              r_fcs;        // frame check sequence
    reg [95:0]              r_ipg;        // inter packet gap
    reg [3:0]               r_stage;
    reg [7:0]               r_data;
    reg [23:0]              r_offset;

    `define IDLE            4'd0
    `define PREAMBLE        4'd1
    `define SFD             4'd2
    `define MACDEST         4'd3
    `define MACSRC          4'd4
    `define ETHERTYPE       4'd5
    `define PAYLOAD         4'd6
    `define FCS             4'd7
    `define IPG             4'd8

    assign out_tx_ready = r_tx_ready;
    assign out_txen = r_txen;
    assign out_txd = r_data;

    initial begin
        r_data <= 8'd0;
        r_data[0] <= 0;
        r_txen = 0;
        r_tx_ready = 1;
        r_dest_mac <= 48'd0; // TODO
        r_src_mac <= 48'd0; // TODO
        r_ether_type <= 16'd0; // TODO
        r_preamble <= 56'b10101010_10101010_10101010_10101010_10101010_10101010_10101010;
        r_sfd <= 8'b10101011;
        r_ipg <= 96'd0;
        r_stage <= 4'd0;
        r_offset <= 0;
    end

    always @(posedge in_clk) begin
        if (in_txen) begin
            if (r_stage == `IDLE)
                r_stage = `PREAMBLE;

            case (r_stage)
                `PREAMBLE: begin
                    r_txen <= 1;
                    r_tx_ready <= 0;
                    // r_data = 8'd0;
                    r_data <= r_preamble[(6-r_offset)*8 +: 8];
                    $display("val is %b", r_preamble[(6-r_offset)*8 +: 8]);
                    r_offset += 1;
                    if (r_offset >= 7) begin
                        r_offset <= 0;
                        r_stage <= `SFD;
                    end
                end

                `SFD: begin
                    r_txen <= 1;
                    r_tx_ready <= 0;
                    r_data <= r_sfd;
                    r_stage <= `MACDEST;
                end

                `MACDEST: begin
                    r_txen <= 1;
                    r_tx_ready <= 0;
                    r_data <= r_dest_mac[(5-r_offset)*8 +: 8];
                    r_offset += 1;
                    if (r_offset >= 6) begin
                        r_offset <= 0;
                        r_stage <= `MACSRC;
                    end
                end

                `MACSRC: begin
                    r_txen <= 1;
                    r_tx_ready <= 0;
                    r_data <= r_src_mac[(5-r_offset)*8 +: 8];
                    r_offset += 1;
                    if (r_offset >= 6) begin
                        r_offset <= 0;
                        r_stage <= `ETHERTYPE;
                    end
                end

                `ETHERTYPE: begin
                    r_txen <= 1;
                    r_tx_ready <= 0;
                    r_data <= r_ether_type[(1-r_offset)*8 +: 8];
                    r_offset += 1;
                    if (r_offset >= 2) begin
                        r_offset <= 0;
                        r_stage <= `PAYLOAD;
                    end
                end

                `PAYLOAD: begin
                    r_txen <= 1;
                    r_tx_ready <= 1;
                    r_data <= in_txd;
                end

                default: begin
                    $finish;
                end
            endcase
        end else begin // in_txen = 0
            case (r_stage)
                // We've received a 0 for txen, which means the payload has ended.
                `PAYLOAD: begin
                    r_txen <= 1;
                    r_tx_ready <= 1;
                    r_stage <= `IPG;
                end

                `IPG: begin
                    r_txen <= 1;
                    r_tx_ready <= 0;
                    r_data <= r_ipg[(11-r_offset)*8 +: 8];
                    r_offset += 1;
                    if (r_offset >= 12) begin
                        r_data <= 8'd0;
                        r_txen <= 0;
                        r_stage <= `IDLE;
                    end
                end

                default: begin
                    r_stage <= `IDLE;
                    r_txen <= 0;
                    r_tx_ready <= 1;
                end
            endcase
        end
    end
endmodule

04/ethernet/phy_tx.v
module phy_tx(
    input   wire        in_txen,
    input   wire [7:0]  in_txd,
    output  wire        out_txc,
    output  wire        out_txen,
    output  wire [7:0]  out_txd
    );

    reg clock;
    reg r_txen;
    reg [7:0] r_txd;

    assign out_txc = clock;
    assign out_txen = r_txen;
    assign out_txd = r_txd;

    initial begin
        clock <= 0;
    end

    always begin
        #10 clock = ~clock;
        r_txen <= in_txen;
        r_txd <= in_txd;
    end
endmodule

04/ethernet/phy_rx.v
// The PHY receives data from the wire and transmits it to the MAC. This module handles this signal
// along with generating the receive clock which is an output of the PHY.
module phy_rx(
    input   wire        in_rxen,
    input   wire [7:0]  in_rxd,
    output  wire        out_rxc,
    output  wire        out_rxdv,
    output  wire [7:0]  out_rxd,
    output  wire        out_rxer,
    output  wire        out_crs
    );

    reg clock;
    reg r_rxdv;
    reg [7:0] r_rxd;
    reg r_rxer;
    reg r_crs;

    assign out_rxc = clock;
    assign out_rxdv = r_rxdv;
    assign out_rxd = r_rxd;
    assign out_rxer = r_rxer;
    assign out_crs = r_crs;

    initial begin
        clock <= 0;
        r_rxdv <= 1; // TODO
        r_rxer <= 0; // TODO
        r_crs <= 0;
    end

    always begin
        #10 clock = ~clock;
        r_rxd <= in_rxd;
        r_crs <= in_rxen;
    end
endmodule

04/ethernet/phy.v
`include "phy_tx.v"
`include "phy_rx.v"

// The Ethernet PHY is a component that operates at the physical layer of the OSI network model.
// It implements the physical layer portion of the Ethernet. Its purpose is to provide analog signal
// physical access to the link. It is usually interfaced with a media-independent interface (MII)
// to a MAC chip in a microcontroller or another system that takes care of the higher layer functions.
//
// More specifically, the Ethernet PHY is a chip that implements the hardware send and receive function
// of Ethernet frames; it interfaces between the analog domain of Ethernet's line modulation and the
// digital domain of link-layer packet signaling. The PHY usually does not handle MAC addressing,
// as that is the link layer's job. Similarly, Wake-on-LAN and Boot ROM functionality is implemented
// in the network interface card (NIC), which may have PHY, MAC, and other functionality integrated
// into one chip or as separate chips.
//
// https://en.wikipedia.org/wiki/Physical_layer#PHY
module phy(
    input   wire        in_txen,    // mii/mac to phy transmit enable
    input   wire [7:0]  in_txd,     // mii/mac to phy transmit data
    input   wire        in_rxen,    // wire to phy receive enable
    input   wire [7:0]  in_rxd,     // wire to phy receive data
    output  wire        out_txc,    // transmit clock (phy to mii/mac)
    output  wire        out_txen,   // phy to wire transmit enable
    output  wire [7:0]  out_txd,    // phy to wire transmit data
    output  wire        out_rxc,    // receive clock (phy to mac/mii)
    output  wire        out_rxdv,   // phy to mii/mac receive data valid
    output  wire [7:0]  out_rxd,    // phy to mii/mac receive data
    output  wire        out_rxer,   // phy to mii/mac receiver err
    output  wire        out_crs     // phy to mii/mac carrier sense
    );

    // Receive data from analog wire and output to mii
    phy_rx phy_rx(in_rxen, in_rxd, out_rxc, out_rxdv, out_rxd, our_rxer, out_crs);

    // Transmit data from Mii to analog wire
    phy_tx phy_tx(in_txen, in_txd, out_txc, out_txen, out_txd);

endmodule

04/ethernet/mac_rx.v
// When data is received from the from the PHY, we need to deconstruct the frame into it's 
// constituents for the MII to pass it forward
module mac_rx(
    input  wire          in_rxc,
    input  wire          in_rxdv,    // receive data valid
    input  wire [7:0]    in_rxd,     // receive data
    input  wire          in_rxer,    // receive error
    input  wire          in_crs,     // carrier sense
    output wire          out_txen,   // transmit enable
    output wire [7:0]    out_txd     // transmit data
    );


    reg                     r_txen;
    reg [7:0]               r_txd;
    reg [55:0]              r_preamble;
    reg [7:0]               r_sfd;        // start frame delimiter
    reg [47:0]              r_dest_mac;
    reg [47:0]              r_src_mac;
    reg [15:0]              r_ether_type;
    reg [7:0]               r_payload;    // min is 46 octets and max is 1500 octets
    reg [31:0]              r_fcs;        // frame check sequence
    reg [95:0]              r_ipg;        // inter packet gap
    reg [3:0]               r_stage;
    reg [7:0]               r_data;
    reg [11:0]              r_offset;

    `define IDLE            4'd0
    `define PREAMBLE        4'd1
    `define SFD             4'd2
    `define MACDEST         4'd3
    `define MACSRC          4'd4
    `define ETHERTYPE       4'd5
    `define PAYLOAD         4'd6
    `define FCS             4'd7
    `define IPG             4'd8

    initial begin
        r_stage = `IDLE;
        r_offset = 12'd0;
    end

    assign out_txen = r_txen;
    assign out_txd = r_txd;

    always @(posedge in_rxc) begin
        if (in_crs) begin
            if (r_stage == `IDLE)
                r_stage = `PREAMBLE;

            case (r_stage)
                `IDLE: begin
                    r_txen = 1'b0;
                    r_offset = 12'd0;
                end

                `PREAMBLE: begin
                    r_txen = 1'b0;
                    r_preamble[(6-r_offset)*8 +: 8] = in_rxd;
                    r_offset += 12'd1;
                    if (r_offset == 12'd7) begin
                        if (r_preamble != 56'b10101010_10101010_10101010_10101010_10101010_10101010_10101010)
                            #10000 $finish;
                        r_offset = 12'd0;
                        r_stage = `SFD;
                    end
                end

                `SFD: begin
                    r_txen = 1'b0;
                    r_sfd = in_rxd;
                    r_offset += 12'd1;
                    if (r_offset == 1) begin
                        r_offset = 12'd0;
                        r_stage = `MACDEST;
                    end
                end

                `MACDEST: begin
                    r_txen = 1'b0;
                    r_dest_mac[(5-r_offset)*8 +: 8] = in_rxd;
                    r_offset += 12'd1;
                    if (r_offset == 12'd6) begin
                        r_offset = 12'd0;
                        r_stage = `MACSRC;
                    end
                end

                `MACSRC: begin
                    r_txen = 1'b0;
                    r_src_mac[(5-r_offset)*8 +: 8] = in_rxd;
                    r_offset += 12'd1;
                    if (r_offset == 12'd6) begin
                        r_offset = 12'd0;
                        r_stage = `ETHERTYPE;
                    end
                end

                `ETHERTYPE: begin
                    r_txen = 1'b0;
                    r_ether_type[(1-r_offset)*8 +: 8] = in_rxd;
                    r_offset += 12'd1;
                    if (r_offset == 12'd2) begin
                        r_offset = 12'd0;
                        r_stage = `PAYLOAD;
                    end
                end

                `PAYLOAD: begin
                    r_txen = 1'b1;
                    // We tell the end of the frame either by carrier signal loss or IPG transmission (96 0 bits)
                    r_txd = in_rxd;
                    r_ipg[(11-r_offset)*8 +: 8] = in_rxd;
                    r_offset += 1;
                    if (r_offset >= 11 && r_ipg == 96'd0) begin // or end of frame char
                        r_stage = `IPG;
                    end else if (r_offset >= 11) begin
                        r_offset -= 1;
                        r_ipg = {r_ipg[87:0], 8'h11};
                    end
                end

                `IPG: begin
                    // 96-bit idle time between packets for reset have been received
                    r_stage = `IDLE;
                    r_offset = 12'd0;
                    r_ipg = 96'd1;
                end
            endcase
        end else begin
            r_stage = `IDLE;
            r_offset = 12'd0;
        end
    end

endmodule

04/ethernet/mac.v
`include "mac_rx.v"
`include "mac_tx.v"

// The MAC sublayer provides a control abstraction of the physical layer such that the complexities
// of physical link control are invisible to the LLC and upper layers of the network stack. Thus any
// LLC sublayer (and higher layers) may be used with any MAC. In turn, the medium access control block
// is formally connected to the PHY via a media-independent interface.
//
// When sending data to another device on the network, the MAC sublayer encapsulates higher-level
// frames into frames appropriate for the transmission medium (i.e. the MAC adds a syncword preamble
// and also padding if necessary), adds a frame check sequence to identify transmission errors, and
// then forwards the data to the physical layer as soon as the appropriate channel access method permits it.
//
// When receiving data from the physical layer, the MAC block ensures data integrity by verifying the
// sender's frame check sequences, and strips off the sender's preamble and padding before passing
// the data up to the higher layers.
//
// https://en.wikipedia.org/wiki/Medium_access_control
module mac(
    input   wire        in_txc,         // transmit clock (higher layer to mac)
    input   wire        in_txen,        // higher layer to mac transmit enable
    input   wire [7:0]  in_txd,         // higher layer to mac transmit data
    input   wire        in_rxc,         // receive clock (mii/phy to mac)
    input   wire        in_rxdv,        // mii/phy to mac receive data valid
    input   wire [7:0]  in_rxd,         // mii/phy to mac receive data
    input   wire        in_rxer,        // mii/phy to mac receive err
    input   wire        in_crs,         // mii/phy to mac carrier sense
    output  wire        out_tx_ready,   // mac to higher layer signalling payload can be received
    output  wire        out_txen,       // mac to mii/phy transmit enable
    output  wire [7:0]  out_txd,        // mac to mii/phy transmit data
    output  wire        out_rxen,       // mac to data-link layer receive enable
    output  wire [7:0]  out_rxd         // mac to data-link layer receive data
    );

    // When data is received from the from the MII(PHY), we need to deconstruct the frame into it's
    // constituents for the MII to pass it forward to the data-link layer of the OSI model.
    mac_rx mac_rx(in_rxc, in_rxdv, in_rxd, in_rxer, in_crs, out_rxen, out_rxd);

    // When data is received from the data-link layer of the OSI, we need to construct an ethernet
    // frame and pass it to the MII so that it can forward it to the PHY.
    mac_tx mac_tx(in_txc, in_txen, in_txd, out_tx_ready, out_txen, out_txd);

endmodule

04/ethernet/eth_controller.v
`include "mac.v"
`include "phy.v"

// Encapsulates: Data-link layer <-> MAC <-> MII <-> PHY <-> Wire
// Inputs/Outputs:
// - Higher layer
// - Wire
module eth_controller(
    input   wire          in_txen,      // mcu/cpu to mac transmit enable
    input   wire [7:0]    in_txd,       // mcu/cpu to mac transmit data
    input   wire          in_rxen,      // wire to phy receive enable
    input   wire [7:0]    in_rxd,       // wire to phy receive data
    output  wire          out_tx_ready, // mac to mcu/cpu transmit ready (1 after preamble etc has been sent)
    output  wire          out_dll_rxen, // mac to data-link layer receive enable
    output  wire [7:0]    out_dll_rxd,  // mac to data-link layer receive data
    output  wire          out_wire_txen,// phy to wire transmit enable
    output  wire [7:0]    out_wire_txd  // phy to wire transmit data
    );

    // We've included the MII in this module itself. It is essentially common wires between the MAC
    // and PHY. Since we're instantiating them here, it makes sense to connect them here to.
    //
    // The media-independent interface (MII) is a standard interface to connect a Ethernet media access 
    // control (MAC) block to a PHY chip.
    // The original MII transfers network data using 4-bit nibbles in each direction (4 transmit data 
    // bits, 4 receive data bits). The data is clocked at 25 MHz to achieve 100 Mbit/s throughput.
    // https://en.wikipedia.org/wiki/Media-independent_interface
    //
    // The transmit clock is a free-running clock generated by the PHY based on the link speed
    // (25 MHz for 100 Mbit/s, 2.5 MHz for 10 Mbit/s).
    // The remaining transmit signals are driven by the MAC synchronously on the rising edge of TXC.
    // This arrangement allows the MAC to operate without having to be aware of the link speed.
    // The transmit enable signal is held high during frame transmission and low when the transmitter
    // is idle.
    wire        w_txc;      // transmit clock
    wire        w_txen;     // transmit enable
    wire [7:0]  w_txd;      // transmit data

    // The first seven receiver signals are entirely analogous to the transmitter signals, except
    // RX_ER is not optional and used to indicate the received signal could not be decoded to valid
    // data. The receive clock is recovered from the incoming signal during frame reception. When
    // no clock can be recovered (i.e. when the medium is silent), the PHY must present a free-running
    // clock as a substitute.
    wire        w_rxc;      // receive clock
    wire        w_rxdv;     // receive data valid
    wire [7:0]  w_rxd;      // receive data
    wire        w_rxer;     // receive error
    wire        w_crs;      // carrier sense

    mac mac(
        .in_txc(w_txc),
        .in_txen(in_txen),
        .in_txd(in_txd),
        .in_rxc(w_rxc),
        .in_rxdv(w_rxdv),
        .in_rxd(w_rxd),
        .in_rxer(w_rxer),
        .in_crs(w_crs),
        .out_tx_ready(out_tx_ready),
        .out_txen(w_txen),
        .out_txd(w_txd),
        .out_rxen(out_dll_rxen),
        .out_rxd(out_dll_rxd)
    );

    phy phy(
        .in_txen(w_txen),
        .in_txd(w_txd),
        .in_rxen(in_rxen),
        .in_rxd(in_rxd),
        .out_txc(w_txc),
        .out_txen(out_wire_txen),
        .out_txd(out_wire_txd),
        .out_rxc(w_rxc),
        .out_rxdv(w_rxdv),
        .out_rxd(w_rxd),
        .out_rxer(w_rxer),
        .out_crs(w_crs)
    );

endmodule

04/ethernet/tb.v
`include "eth_controller.v"

module tb;
    wire          in_txen;      // mcu/cpu transmit enable
    wire [7:0]    in_txd;       // mcu/cpu transmit data
    wire          in_rxen;      // wire receive enable
    wire [7:0]    in_rxd;       // wire receive data
    wire          out_tx_ready; // mcu/cpu transmit ready (1 after preamble etc has been sent)
    wire          out_wire_txen;// phy to wire transmit enable
    wire [7:0]    out_wire_txd; // phy to wire transmit data
    wire          out_dll_rxen; // mac to data-link layer receive enable
    wire [7:0]    out_dll_rxd;  // mac to data-link layer receive data

    reg           clock;
    reg [23:0]    r_offset;
    reg           r_txen;
    reg [7:0]     r_txd;
    reg [159:0]   r_input_data;

    wire          w_rx_ready;
    wire          w_rxen;
    wire [7:0]    w_rxd;

    reg           r_dll_en = 0;
    reg [7:0]     r_dll_d = 0;

    assign in_txen = r_txen;
    assign in_txd = r_txd;
    assign in_rxen = w_rxen;
    assign in_rxd = w_rxd;

    eth_controller eth_controller(
        .in_txen(in_txen),
        .in_txd(in_txd),
        .in_rxen(in_rxen),
        .in_rxd(in_rxd),
        .out_tx_ready(out_tx_ready),
        .out_dll_rxen(out_dll_rxen),
        .out_dll_rxd(out_dll_rxd),
        .out_wire_txen(out_wire_txen),
        .out_wire_txd(out_wire_txd)
    );

    initial begin
        $dumpfile("tb.vcd");
        $dumpvars;
    end

    initial begin
        clock = 0;
        r_offset = 0;
        r_txen = 0;
        r_input_data = 160'h00_01_02_03_04_05_06_07_08_09_0a_0b_0c_0d_0e_0f_10_11_12_13;
        r_txen = 1;
    end

    always begin
        #10 clock = ~clock;
    end

    always @(posedge clock) begin
        if (r_txen && out_tx_ready) begin
            r_txd = r_input_data[(19-r_offset) * 8 +: 8];
            r_offset += 1;
            $display("Packet from link layer is %h", r_txd);
            if (r_offset >= 9) begin
                r_offset = 0;
                r_txen <= 0;
            end
        end else begin
            if (~r_txen && ~w_rxen) begin
                #100 r_dll_en = 1;
            end
        end
    end

    // Simulate external Data link layer to MAC connection and transmit data
    // through wire.
    mac_tx mac_tx(clock, r_dll_en, r_dll_d, w_rx_ready, w_rxen, w_rxd);

    always @(posedge clock) begin
        if (r_dll_en && w_rx_ready) begin
            r_dll_d = r_input_data[(9-r_offset) * 8 +: 8];
            r_offset += 1;
            $display("Packet from wire is %h", r_dll_d);
            if (r_offset >= 9)
                #100 r_dll_en = 0;
        end else begin
            if (~r_txen && r_offset >= 9)
                #10000 $finish;
        end
    end
endmodule

04/ethernet/tb.vcd
$date
	Sun Jun 26 21:39:56 2022
$end
$version
	Icarus Verilog
$end
$timescale
	1s
$end
$scope module tb $end
$var wire 8 ! in_rxd [7:0] $end
$var wire 1 " in_rxen $end
$var wire 8 # in_txd [7:0] $end
$var wire 1 $ in_txen $end
$var wire 1 % w_rxen $end
$var wire 8 & w_rxd [7:0] $end
$var wire 1 ' w_rx_ready $end
$var wire 1 ( out_wire_txen $end
$var wire 8 ) out_wire_txd [7:0] $end
$var wire 1 * out_tx_ready $end
$var wire 1 + out_dll_rxen $end
$var wire 8 , out_dll_rxd [7:0] $end
$var reg 1 - clock $end
$var reg 8 . r_dll_d [7:0] $end
$var reg 1 / r_dll_en $end
$var reg 160 0 r_input_data [159:0] $end
$var reg 24 1 r_offset [23:0] $end
$var reg 8 2 r_txd [7:0] $end
$var reg 1 3 r_txen $end
$scope module eth_controller $end
$var wire 8 4 in_rxd [7:0] $end
$var wire 1 " in_rxen $end
$var wire 8 5 in_txd [7:0] $end
$var wire 1 $ in_txen $end
$var wire 1 6 w_rxer $end
$var wire 1 7 w_txen $end
$var wire 8 8 w_txd [7:0] $end
$var wire 1 9 w_txc $end
$var wire 1 : w_rxdv $end
$var wire 8 ; w_rxd [7:0] $end
$var wire 1 < w_rxc $end
$var wire 1 = w_crs $end
$var wire 1 ( out_wire_txen $end
$var wire 8 > out_wire_txd [7:0] $end
$var wire 1 * out_tx_ready $end
$var wire 1 + out_dll_rxen $end
$var wire 8 ? out_dll_rxd [7:0] $end
$scope module mac $end
$var wire 1 6 in_rxer $end
$var wire 8 @ in_txd [7:0] $end
$var wire 1 $ in_txen $end
$var wire 1 7 out_txen $end
$var wire 8 A out_txd [7:0] $end
$var wire 1 * out_tx_ready $end
$var wire 1 + out_rxen $end
$var wire 8 B out_rxd [7:0] $end
$var wire 1 9 in_txc $end
$var wire 1 : in_rxdv $end
$var wire 8 C in_rxd [7:0] $end
$var wire 1 < in_rxc $end
$var wire 1 = in_crs $end
$scope module mac_rx $end
$var wire 1 6 in_rxer $end
$var wire 8 D out_txd [7:0] $end
$var wire 1 + out_txen $end
$var wire 1 : in_rxdv $end
$var wire 8 E in_rxd [7:0] $end
$var wire 1 < in_rxc $end
$var wire 1 = in_crs $end
$var reg 48 F r_dest_mac [47:0] $end
$var reg 16 G r_ether_type [15:0] $end
$var reg 96 H r_ipg [95:0] $end
$var reg 12 I r_offset [11:0] $end
$var reg 56 J r_preamble [55:0] $end
$var reg 8 K r_sfd [7:0] $end
$var reg 48 L r_src_mac [47:0] $end
$var reg 4 M r_stage [3:0] $end
$var reg 8 N r_txd [7:0] $end
$var reg 1 O r_txen $end
$upscope $end
$scope module mac_tx $end
$var wire 8 P in_txd [7:0] $end
$var wire 1 $ in_txen $end
$var wire 1 * out_tx_ready $end
$var wire 8 Q out_txd [7:0] $end
$var wire 1 7 out_txen $end
$var wire 1 9 in_clk $end
$var reg 8 R r_data [7:0] $end
$var reg 48 S r_dest_mac [47:0] $end
$var reg 16 T r_ether_type [15:0] $end
$var reg 96 U r_ipg [95:0] $end
$var reg 24 V r_offset [23:0] $end
$var reg 56 W r_preamble [55:0] $end
$var reg 8 X r_sfd [7:0] $end
$var reg 48 Y r_src_mac [47:0] $end
$var reg 4 Z r_stage [3:0] $end
$var reg 1 [ r_tx_ready $end
$var reg 1 \ r_txen $end
$upscope $end
$upscope $end
$scope module phy $end
$var wire 8 ] in_rxd [7:0] $end
$var wire 1 " in_rxen $end
$var wire 8 ^ in_txd [7:0] $end
$var wire 1 7 in_txen $end
$var wire 1 6 out_rxer $end
$var wire 1 ( out_txen $end
$var wire 8 _ out_txd [7:0] $end
$var wire 1 9 out_txc $end
$var wire 1 : out_rxdv $end
$var wire 8 ` out_rxd [7:0] $end
$var wire 1 < out_rxc $end
$var wire 1 = out_crs $end
$var wire 1 a our_rxer $end
$scope module phy_rx $end
$var wire 8 b in_rxd [7:0] $end
$var wire 1 " in_rxen $end
$var wire 1 = out_crs $end
$var wire 1 < out_rxc $end
$var wire 8 c out_rxd [7:0] $end
$var wire 1 : out_rxdv $end
$var wire 1 a out_rxer $end
$var reg 1 d clock $end
$var reg 1 e r_crs $end
$var reg 8 f r_rxd [7:0] $end
$var reg 1 g r_rxdv $end
$var reg 1 h r_rxer $end
$upscope $end
$scope module phy_tx $end
$var wire 8 i in_txd [7:0] $end
$var wire 1 7 in_txen $end
$var wire 1 9 out_txc $end
$var wire 8 j out_txd [7:0] $end
$var wire 1 ( out_txen $end
$var reg 1 k clock $end
$var reg 8 l r_txd [7:0] $end
$var reg 1 m r_txen $end
$upscope $end
$upscope $end
$upscope $end
$scope module mac_tx $end
$var wire 1 - in_clk $end
$var wire 8 n in_txd [7:0] $end
$var wire 1 / in_txen $end
$var wire 1 ' out_tx_ready $end
$var wire 1 % out_txen $end
$var wire 8 o out_txd [7:0] $end
$var reg 8 p r_data [7:0] $end
$var reg 48 q r_dest_mac [47:0] $end
$var reg 16 r r_ether_type [15:0] $end
$var reg 96 s r_ipg [95:0] $end
$var reg 24 t r_offset [23:0] $end
$var reg 56 u r_preamble [55:0] $end
$var reg 8 v r_sfd [7:0] $end
$var reg 48 w r_src_mac [47:0] $end
$var reg 4 x r_stage [3:0] $end
$var reg 1 y r_tx_ready $end
$var reg 1 % r_txen $end
$upscope $end
$upscope $end
$enddefinitions $end
#0
$dumpvars
1y
b0 x
b0 w
b10101011 v
b10101010101010101010101010101010101010101010101010101010 u
b0 t
b0 s
b0 r
b0 q
b0 p
b0 o
b0 n
xm
bx l
0k
bx j
b0 i
0h
1g
bx f
0e
0d
bx c
b0 b
0a
bx `
bx _
b0 ^
b0 ]
0\
1[
b0 Z
b0 Y
b10101011 X
b10101010101010101010101010101010101010101010101010101010 W
b0 V
b0 U
b0 T
b0 S
b0 R
b0 Q
bx P
xO
bx N
b0 M
bx L
bx K
bx J
b0 I
bx H
bx G
bx F
bx E
bx D
bx C
bx B
b0 A
bx @
bx ?
bx >
0=
0<
bx ;
1:
09
b0 8
07
z6
bx 5
b0 4
13
bx 2
b0 1
b1000000100000001100000100000001010000011000000111000010000000100100001010000010110000110000001101000011100000111100010000000100010001001000010011 0
0/
b0 .
0-
bx ,
x+
1*
bx )
x(
1'
b0 &
0%
1$
bx #
0"
b0 !
$end
#10
b10101010 8
b10101010 A
b10101010 Q
b10101010 ^
b10101010 i
b10101010 R
0*
0[
17
1\
b0 )
b0 >
b0 _
b0 j
b0 l
0(
0m
b0 ;
b0 C
b0 E
b0 `
b0 c
b0 f
b1 1
b0 #
b0 5
b0 @
b0 P
b0 2
b1 V
b1 Z
1-
19
1k
1<
1d
#20
b10101010 )
b10101010 >
b10101010 _
b10101010 j
b10101010 l
1(
1m
0-
09
0k
0<
0d
#30
b10 V
1-
19
1k
1<
1d
#40
0-
09
0k
0<
0d
#50
b11 V
1-
19
1k
1<
1d
#60
0-
09
0k
0<
0d
#70
b100 V
1-
19
1k
1<
1d
#80
0-
09
0k
0<
0d
#90
b101 V
1-
19
1k
1<
1d
#100
0-
09
0k
0<
0d
#110
b110 V
1-
19
1k
1<
1d
#120
0-
09
0k
0<
0d
#130
b10 Z
b0 V
1-
19
1k
1<
1d
#140
0-
09
0k
0<
0d
#150
b11 Z
b10101011 8
b10101011 A
b10101011 Q
b10101011 ^
b10101011 i
b10101011 R
1-
19
1k
1<
1d
#160
b10101011 )
b10101011 >
b10101011 _
b10101011 j
b10101011 l
0-
09
0k
0<
0d
#170
b0 8
b0 A
b0 Q
b0 ^
b0 i
b0 R
b1 V
1-
19
1k
1<
1d
#180
b0 )
b0 >
b0 _
b0 j
b0 l
0-
09
0k
0<
0d
#190
b10 V
1-
19
1k
1<
1d
#200
0-
09
0k
0<
0d
#210
b11 V
1-
19
1k
1<
1d
#220
0-
09
0k
0<
0d
#230
b100 V
1-
19
1k
1<
1d
#240
0-
09
0k
0<
0d
#250
b101 V
1-
19
1k
1<
1d
#260
0-
09
0k
0<
0d
#270
b100 Z
b0 V
1-
19
1k
1<
1d
#280
0-
09
0k
0<
0d
#290
b1 V
1-
19
1k
1<
1d
#300
0-
09
0k
0<
0d
#310
b10 V
1-
19
1k
1<
1d
#320
0-
09
0k
0<
0d
#330
b11 V
1-
19
1k
1<
1d
#340
0-
09
0k
0<
0d
#350
b100 V
1-
19
1k
1<
1d
#360
0-
09
0k
0<
0d
#370
b101 V
1-
19
1k
1<
1d
#380
0-
09
0k
0<
0d
#390
b101 Z
b0 V
1-
19
1k
1<
1d
#400
0-
09
0k
0<
0d
#410
b1 V
1-
19
1k
1<
1d
#420
0-
09
0k
0<
0d
#430
b110 Z
b0 V
1-
19
1k
1<
1d
#440
0-
09
0k
0<
0d
#450
1*
1[
1-
19
1k
1<
1d
#460
0-
09
0k
0<
0d
#470
b10 1
b1 #
b1 5
b1 @
b1 P
b1 2
1-
19
1k
1<
1d
#480
0-
09
0k
0<
0d
#490
b1 8
b1 A
b1 Q
b1 ^
b1 i
b1 R
b11 1
b10 #
b10 5
b10 @
b10 P
b10 2
1-
19
1k
1<
1d
#500
b1 )
b1 >
b1 _
b1 j
b1 l
0-
09
0k
0<
0d
#510
b10 8
b10 A
b10 Q
b10 ^
b10 i
b10 R
b100 1
b11 #
b11 5
b11 @
b11 P
b11 2
1-
19
1k
1<
1d
#520
b10 )
b10 >
b10 _
b10 j
b10 l
0-
09
0k
0<
0d
#530
b11 8
b11 A
b11 Q
b11 ^
b11 i
b11 R
b101 1
b100 #
b100 5
b100 @
b100 P
b100 2
1-
19
1k
1<
1d
#540
b11 )
b11 >
b11 _
b11 j
b11 l
0-
09
0k
0<
0d
#550
b100 8
b100 A
b100 Q
b100 ^
b100 i
b100 R
b110 1
b101 #
b101 5
b101 @
b101 P
b101 2
1-
19
1k
1<
1d
#560
b100 )
b100 >
b100 _
b100 j
b100 l
0-
09
0k
0<
0d
#570
b101 8
b101 A
b101 Q
b101 ^
b101 i
b101 R
b111 1
b110 #
b110 5
b110 @
b110 P
b110 2
1-
19
1k
1<
1d
#580
b101 )
b101 >
b101 _
b101 j
b101 l
0-
09
0k
0<
0d
#590
b110 8
b110 A
b110 Q
b110 ^
b110 i
b110 R
b1000 1
b111 #
b111 5
b111 @
b111 P
b111 2
1-
19
1k
1<
1d
#600
b110 )
b110 >
b110 _
b110 j
b110 l
0-
09
0k
0<
0d
#610
0$
03
b111 8
b111 A
b111 Q
b111 ^
b111 i
b111 R
b0 1
b1000 #
b1000 5
b1000 @
b1000 P
b1000 2
1-
19
1k
1<
1d
#620
b111 )
b111 >
b111 _
b111 j
b111 l
0-
09
0k
0<
0d
#630
b1000 Z
1-
19
1k
1<
1d
#640
0-
09
0k
0<
0d
#650
b0 8
b0 A
b0 Q
b0 ^
b0 i
b0 R
0*
0[
b1 V
1-
19
1k
1<
1d
#660
b0 )
b0 >
b0 _
b0 j
b0 l
0-
09
0k
0<
0d
#670
b10 V
1-
19
1k
1<
1d
#680
0-
09
0k
0<
0d
#690
b11 V
1-
19
1k
1<
1d
#700
0-
09
0k
0<
0d
#710
b100 V
1-
19
1k
1<
1d
#720
0-
09
0k
0<
0d
#730
b10101010 !
b10101010 4
b10101010 ]
b10101010 b
b10101010 &
b10101010 o
b10101010 p
0'
0y
1"
1%
b1 t
b1 x
b1 1
b1010 .
b1010 n
b101 V
1-
19
1k
1<
1d
1/
#740
1=
1e
b10101010 ;
b10101010 C
b10101010 E
b10101010 `
b10101010 c
b10101010 f
0-
09
0k
0<
0d
#750
b10 t
b110 V
b1 I
b10101010xxxxxxxxxxxxxxxxxxxxxxxxxxxxxxxxxxxxxxxxxxxxxxxx J
0+
0O
b1 M
1-
19
1k
1<
1d
#760
0-
09
0k
0<
0d
#770
b11 t
b111 V
b10 I
b1010101010101010xxxxxxxxxxxxxxxxxxxxxxxxxxxxxxxxxxxxxxxx J
1-
19
1k
1<
1d
#780
0-
09
0k
0<
0d
#790
b100 t
b1000 V
b11 I
b101010101010101010101010xxxxxxxxxxxxxxxxxxxxxxxxxxxxxxxx J
1-
19
1k
1<
1d
